Workbook

Sheet Read me
B2: Monid Finance Tools
B5: Scope | C5: 70 retrievable finance tools; 71 advertised. Company/market/news: 55. Insider/ownership: 15. Snapshot 9 September 2026.
B8: Start here | C8: Company tools and Insider tools contain the complete inventory. Provider evidence supplies inherited coverage, provenance, rights and audience. Sources contains primary links.
B11: Cost controls | C11: Edit blue cells in Assumptions and Costs. Profiles are formulas tied to assumptions. Costs shows occasional research and shared regular feeds for 10 and 100 users.
B14: Selected budget | C14: Set Include = 1 for tools you actually want. Default selected budget is zero. Reference totals enable all 70 overlapping tools and are NOT recommended bundles.
B17: Coverage | C17: Website ticker/profile counts do not prove Monid company coverage. Every exact per-tool supported-company count remains unverified.
B20: Permission | C20: No customer-display/storage grant established for these Monid connectors. Paying call charges does not establish news-body/image rights or publisher subscription access.
B23: Freshness | C23: No paid endpoint benchmark, measured error rate or confirmed real-time delivery SLA. SECForm4 public delay does not prove the tier Monid uses.
B26: Scenario limits | C26: One page and one entity per call, no retries by default. Fees exclude licences, tax, infrastructure, AI processing and backfill. Changing scopes/intervals is not proof of API capacity.
B29: Recalculation | C29: Formula cells include cached default results. Excel recalculates when opened/edited. Do not treat saved default results as updated after modifying the file with a non-calculating library.

Sheet Assumptions
A1: Assumption | B1: Editable value | C1: Meaning / limitation
A2: Users: smaller scenario | B2: 10 | C2: Number of app users; not provider seats.
A3: Users: larger scenario | B3: 100 | C3: Number of app users; not provider seats.
A4: Research lookups / user / workday | B4: 5 | C4: Each lookup calls ONE selected endpoint. A multi-tool page sums those endpoint calls.
A5: Workdays / month | B5: 22 | C5: Budget convention, not the actual exchange/filing calendar.
A6: Calendar days / month | B6: 30 | C6: Budget convention.
A7: Followed security keys / user | B7: 20 | C7: A key identifies one security/company query; not necessarily a unique issuer.
A8: Unique-union ratio | B8: 0.5 | C8: Distinct followed keys / sum of watchlist lengths. Sharing requires permission. Minimum is one full watchlist.
A9: Regular market hours / day | B9: 6.5 | C9: US regular-session budget; extended and global sessions require a larger setting.
A10: Market polling interval: minutes | B10: 5 | C10: Proposed polling only; does not establish real-time data.
A11: News active hours / calendar day | B11: 16 | C11: Hourly news monitoring; not 24-hour coverage.
A12: News polling interval: minutes | B12: 60 | C12: Hourly polling. New items can wait up to a polling interval plus upstream lag.
A13: Filing active hours / workday | B13: 16 | C13: Illustrative window, not an exact EDGAR schedule; gaps need catch-up.
... A20: Premarket hours / workday | B20: 5.5 | C20: Illustrative US premarket monitoring window; confirm source session coverage.

Sheet Profiles
A1: Profile key | B1: Proposed cadence | C1: Scope | D1: Polls / key / month
A2: entity_market | B2: Per security: every 5 min in regular market hours | C2: entity | D2: =Assumptions!$B$9*60/Assumptions!$B$10*Assumptions!$B$5 -> 1716
A3: global_market | B3: Shared market list: every 5 min in regular hours | C3: global | D3: =Assumptions!$B$9*60/Assumptions!$B$10*Assumptions!$B$5 -> 1716
A4: entity_news | B4: Per company: hourly, 16 h/day, 30 days | C4: entity | D4: =Assumptions!$B$11*60/Assumptions!$B$12*Assumptions!$B$6 -> 480
A5: entity_hourly | B5: Per company: hourly, 16 h/day, 22 workdays | C5: entity | D5: =Assumptions!$B$13*60/Assumptions!$B$15*Assumptions!$B$5 -> 352
A6: global_insider | B6: Shared disclosure list: 15 min, 16 h, 22 workdays | C6: global | D6: =Assumptions!$B$13*60/Assumptions!$B$14*Assumptions!$B$5 -> 1408
A7: entity_daily | B7: Per company/security: once daily | C7: entity | D7: =Assumptions!$B$16*Assumptions!$B$6 -> 30
A8: global_daily | B8: Shared directory/calendar/list: once daily | C8: global | D8: =Assumptions!$B$16*Assumptions!$B$6 -> 30
A9: lookup_demand | B9: Demand-only lookup, 50% cache misses | C9: demand | D9: =0 -> 0
A10: entity_crypto | B10: Optional crypto: every 5 min, 24 h/day | C10: entity | D10: =Assumptions!$B$18*60/Assumptions!$B$10*Assumptions!$B$6 -> 8640
A11: entity_onchain | B11: Tokenized/perpetual venues: hourly, 24 h/day | C11: entity | D11: =24*60/Assumptions!$B$19*Assumptions!$B$6 -> 720
A12: global_premarket | B12: Shared premarket list: every 5 min, 5.5 h, 22 days | C12: global | D12: =Assumptions!$B$20*60/Assumptions!$B$10*Assumptions!$B$5 -> 1452

Sheet Company tools
A1: ID | B1: Provider | C1: Endpoint | D1: What it provides | E1: Company coverage | F1: Accuracy assessment | G1: Freshness / real time | H1: Response speed | I1: MVP relevance | J1: Possible platform feature | K1: Specific limitations | L1: Official source status | M1: Permissions | N1: Operational safety | O1: Confirmed users | P1: Intended users (assessment) | Q1: Exact catalogue source
A2: T01 | B2: nasdaq | C2: /get_stock_earnings | D2: Reported earnings and expectations | E2: Unknown Monid count; US exchange-listed source scope, tool dependent. | F2: Good source-checking potential; reconcile selected values to company filings. | G2: Reporting-cycle data, often quarterly/annual; monitor revisions. | H2: Unmeasured: no paid endpoint latency benchmark or confirmed Monid SLA. | I2: High | J2: Company earnings card and results alerts | K2: Actuals and analyst estimates must remain separate; expected dates can change. | L2: See P1 source/provenance assessment; Monid authority unverified. | M2: See P1 rights assessment; customer display/storage grant unverified. | N2: Not security-audited. Server-side credentials, endpoint allowlist, input validation and spending caps proposed; no verified Monid SLA or contractual security assurance. | O2: No named customer verified for this exact Monid connector. | P2: Fundamental analysts and company researchers | Q2: Metadata: T01
A3: T02 | B3: nasdaq | C3: /get_stock_screener | D3: Filter listed stocks | E3: Unknown Monid count; US exchange-listed source scope, tool dependent. | F3: Useful discovery subset; ranking/filter completeness unmeasured. | G3: Depends on underlying fields and refresh schedule; not a full market tape. | H3: Unmeasured: no paid endpoint latency benchmark or confirmed Monid SLA. | I3: Medium | J3: Catalogue discovery and saved screens | K3: Universe, pagination and filter parity with Nasdaq are unverified. | L3: See P1 source/provenance assessment; Monid authority unverified. | M3: See P1 rights assessment; customer display/storage grant unverified. | N3: Not security-audited. Server-side credentials, endpoint allowlist, input validation and spending caps proposed; no verified Monid SLA or contractual security assurance. | O3: No named customer verified for this exact Monid connector. | P3: Investors and company/market researchers | Q3: Metadata: T02
A4: T03 | B4: nasdaq | C4: /get_earnings_calendar | D4: Upcoming earnings dates | E4: Unknown Monid count; US exchange-listed source scope, tool dependent. | F4: Useful for planning; flag estimated, confirmed, postponed and cancelled states. | G4: Event-driven revisions; expected dates can change. | H4: Unmeasured: no paid endpoint latency benchmark or confirmed Monid SLA. | I4: Medium | J4: Shared earnings calendar matched to holdings | K4: Some dates are algorithmic estimates; mark confirmed versus estimated. | L4: See P1 source/provenance assessment; Monid authority unverified. | M4: See P1 rights assessment; customer display/storage grant unverified. | N4: Not security-audited. Server-side credentials, endpoint allowlist, input validation and spending caps proposed; no verified Monid SLA or contractual security assurance. | O4: No named customer verified for this exact Monid connector. | P4: Investors and company/market researchers | Q4: Metadata: T03
A5: T04 | B5: nasdaq | C5: /get_stock_sec_filings | D5: Company filing records and source links | E5: Unknown Monid count; US exchange-listed source scope, tool dependent. | F5: High auditability only when accession/source links survive. | G5: After filing publication, not when the underlying event happened. | H5: Unmeasured: no paid endpoint latency benchmark or confirmed Monid SLA. | I5: High | J5: Company filing timeline and original-document links | K5: General filing discovery; confirm accession IDs, form filters and amendments. | L5: See P1 source/provenance assessment; Monid authority unverified. | M5: See P1 rights assessment; customer display/storage grant unverified. | N5: Not security-audited. Server-side credentials, endpoint allowlist, input validation and spending caps proposed; no verified Monid SLA or contractual security assurance. | O5: No named customer verified for this exact Monid connector. | P5: Investors and company/market researchers | Q5: Metadata: T04
A6: T05 | B6: nasdaq | C6: /get_mutual_fund_quote | D6: Mutual-fund price or NAV snapshot | E6: Unknown Monid count; US exchange-listed source scope, tool dependent. | F6: Check official fund NAV and valuation date. | G6: Periodic NAV; not an intraday equity feed. | H6: Unmeasured: no paid endpoint latency benchmark or confirmed Monid SLA. | I6: Medium; optional feature | J6: Optional fund facts panel | K6: Fund NAV is typically periodic; this is not a live stock quote or company count. | L6: See P1 source/provenance assessment; Monid authority unverified. | M6: See P1 rights assessment; customer display/storage grant unverified. | N6: Not security-audited. Server-side credentials, endpoint allowlist, input validation and spending caps proposed; no verified Monid SLA or contractual security assurance. | O6: No named customer verified for this exact Monid connector. | P6: Investors and company/market researchers | Q6: Metadata: T05
A7: T06 | B7: nasdaq | C7: /get_stock_dividend_history | D7: Past dividend payments | E7: Unknown Monid count; US exchange-listed source scope, tool dependent. | F7: Good source-checking potential; reconcile selected values to company filings. | G7: Reporting-cycle data, often quarterly/annual; monitor revisions. | H7: Unmeasured: no paid endpoint latency benchmark or confirmed Monid SLA. | I7: High | J7: Company income and distribution history | K7: Past dividends do not guarantee future payments; distinguish ex-date and payment date. | L7: See P1 source/provenance assessment; Monid authority unverified. | M7: See P1 rights assessment; customer display/storage grant unverified. | N7: Not security-audited. Server-side credentials, endpoint allowlist, input validation and spending caps proposed; no verified Monid SLA or contractual security assurance. | O7: No named customer verified for this exact Monid connector. | P7: Fundamental analysts and company researchers | Q7: Metadata: T06
A8: T07 | B8: nasdaq | C8: /get_stock_quote | D8: Stock quote snapshot | E8: Unknown Monid count; US exchange-listed source scope, tool dependent. | F8: Useful for a timestamped price display; correctness unmeasured through Monid. | G8: Potentially frequent upstream updates; no verified Monid real-time delivery. | H8: Unmeasured: no paid endpoint latency benchmark or confirmed Monid SLA. | I8: High | J8: Company header and watchlist price card | K8: Website quote updates do not establish Monid feed latency or exchange entitlement. | L8: See P1 source/provenance assessment; Monid authority unverified. | M8: See P1 rights assessment; customer display/storage grant unverified. | N8: Not security-audited. Server-side credentials, endpoint allowlist, input validation and spending caps proposed; no verified Monid SLA or contractual security assurance. | O8: No named customer verified for this exact Monid connector. | P8: Investors and company/market researchers | Q8: Metadata: T07
A9: T08 | B9: nasdaq | C9: /search_symbols | D9: Search security identifiers | E9: Unknown Monid count; US exchange-listed source scope, tool dependent. | F9: Useful candidate matching; validate exchange, instrument type and issuer identifiers. | G9: Mostly reference data; newly listed, delisted and renamed securities need updates. | H9: Unmeasured: no paid endpoint latency benchmark or confirmed Monid SLA. | I9: Medium | J9: Catalogue symbol resolver | K9: Interactive search is not a complete security master; exchange collisions need resolution. | L9: See P1 source/provenance assessment; Monid authority unverified. | M9: See P1 rights assessment; customer display/storage grant unverified. | N9: Not security-audited. Server-side credentials, endpoint allowlist, input validation and spending caps proposed; no verified Monid SLA or contractual security assurance. | O9: No named customer verified for this exact Monid connector. | P9: Catalogue users and data operations | Q9: Metadata: T08
A10: T09 | B10: nasdaq | C10: /get_market_indices | D10: Broad market index overview | E10: Unknown Monid count; US exchange-listed source scope, tool dependent. | F10: Useful for a timestamped price display; correctness unmeasured through Monid. | G10: Potentially frequent upstream updates; no verified Monid real-time delivery. | H10: Unmeasured: no paid endpoint latency benchmark or confirmed Monid SLA. | I10: High | J10: Global markets overview | K10: Index levels are not company coverage; provider-specific index delays apply. | L10: See P1 source/provenance assessment; Monid authority unverified. | M10: See P1 rights assessment; customer display/storage grant unverified. | N10: Not security-audited. Server-side credentials, endpoint allowlist, input validation and spending caps proposed; no verified Monid SLA or contractual security assurance. | O10: No named customer verified for this exact Monid connector. | P10: Investors and company/market researchers | Q10: Metadata: T09
A11: T10 | B11: nasdaq | C11: /get_stock_historical_quotes | D11: Historical stock price observations | E11: Unknown Monid count; US exchange-listed source scope, tool dependent. | F11: Validate adjustments, gaps, timestamps and price units against an authorised reference. | G11: Historical bars; interval size does not prove delivery latency. | H11: Unmeasured: no paid endpoint latency benchmark or confirmed Monid SLA. | I11: High | J11: Company historical price chart | K11: Confirm adjusted prices, corporate actions and maximum history. The same-named Parse wrapper describes end-of-day history only; its relationship to Monid is unverified. | L11: See P1 source/provenance assessment; Monid authority unverified. | M11: See P1 rights assessment; customer display/storage grant unverified. | N11: Not security-audited. Server-side credentials, endpoint allowlist, input validation and spending caps proposed; no verified Monid SLA or contractual security assurance. | O11: No named customer verified for this exact Monid connector. | P11: Investors and company/market researchers | Q11: Metadata: T10
A12: T12 | B12: nasdaq | C12: /get_market_movers | D12: Leading price movers | E12: Unknown Monid count; US exchange-listed source scope, tool dependent. | F12: Useful discovery subset; ranking/filter completeness unmeasured. | G12: Depends on underlying fields and refresh schedule; not a full market tape. | H12: Unmeasured: no paid endpoint latency benchmark or confirmed Monid SLA. | I12: Medium | J12: Market discovery panel | K12: Ranking is a selected subset, not all stocks; volume and reference session matter. | L12: See P1 source/provenance assessment; Monid authority unverified. | M12: See P1 rights assessment; customer display/storage grant unverified. | N12: Not security-audited. Server-side credentials, endpoint allowlist, input validation and spending caps proposed; no verified Monid SLA or contractual security assurance. | O12: No named customer verified for this exact Monid connector. | P12: Investors and company/market researchers | Q12: Metadata: T12
... A56: T59 | B56: defillama | C56: /equities/v1/dimensions | D56: Quarterly/annual revenue, holder-revenue, earnings and share series | E56: Unknown exact count; supported ticker/country directory exists. | F56: Validate methodology, source fields and period consistency. | G56: Dependent on underlying source updates and calculation window. | H56: Unmeasured: no paid endpoint latency benchmark or confirmed Monid SLA. | I56: Medium | J56: Company financial-trend comparisons | K56: Defined financial metric series, not arbitrary operational KPIs or business/geographic segments; validate periods and company completeness. | L56: See P6 source/provenance assessment; Monid authority unverified. | M56: See P6 rights assessment; customer display/storage grant unverified. | N56: Not security-audited. Server-side credentials, endpoint allowlist, input validation and spending caps proposed; no verified Monid SLA or contractual security assurance. | O56: No named customer verified for this exact Monid connector. | P56: Investors and company/market researchers | Q56: Metadata: T59

Sheet Insider tools
A1: ID | B1: Provider | C1: Endpoint | D1: What it provides | E1: Company coverage | F1: Accuracy assessment | G1: Freshness / real time | H1: Response speed | I1: MVP relevance | J1: Possible platform feature | K1: Specific limitations | L1: Official source status | M1: Permissions | N1: Operational safety | O1: Confirmed users | P1: Intended users (assessment) | Q1: Exact catalogue source
A2: T11 | B2: nasdaq | C2: /get_stock_institutional_holdings | D2: Institutional ownership records | E2: Unknown Monid count; US exchange-listed source scope, tool dependent. | F2: Reconcile reporting manager, quarter, security class and amendments. | G2: Periodic, historically reported holdings; not real-time ownership. | H2: Unmeasured: no paid endpoint latency benchmark or confirmed Monid SLA. | I2: Medium | J2: Company ownership and investor changes | K2: Institutional filings describe historical positions; not same-day insider trades. | L2: See P1 source/provenance assessment; Monid authority unverified. | M2: See P1 rights assessment; customer display/storage grant unverified. | N2: Not security-audited. Server-side credentials, endpoint allowlist, input validation and spending caps proposed; no verified Monid SLA or contractual security assurance. | O2: No named customer verified for this exact Monid connector. | P2: Company and institutional-portfolio researchers | Q2: Metadata: T11
A3: T27 | B3: finviz | C3: /get_insider_trading | D3: Recent reported insider transactions | E3: Website: 5,613 stock ticker rows observed; exact Monid/per-tool count unknown. | F3: High auditability with original filing; parsing and transaction interpretation need checks. | G3: Disclosure-lagged; vendor ingestion lag and Monid tier unmeasured. | H3: Unmeasured: no paid endpoint latency benchmark or confirmed Monid SLA. | I3: High | J3: Shared insider activity feed filtered to holdings | K3: Verify original forms, transaction codes, dates and amendments. A same-named Parse sample labels a Form 144 proposed-sale link as Form 4; this is not a tested Monid defect or proof of a completed sale. | L3: See P3 source/provenance assessment; Monid authority unverified. | M3: See P3 rights assessment; customer display/storage grant unverified. | N3: Not security-audited. Server-side credentials, endpoint allowlist, input validation and spending caps proposed; no verified Monid SLA or contractual security assurance. | O3: No named customer verified for this exact Monid connector. | P3: Investors studying executive disclosures | Q3: Metadata: T27
A4: T32 | B4: marketbeat | C4: /get_institutional_ownership | D4: Institutional holders and ownership changes | E4: Website claim: 20,000 company profiles; Monid/per-tool count unknown. | F4: Reconcile reporting manager, quarter, security class and amendments. | G4: Periodic, historically reported holdings; not real-time ownership. | H4: Unmeasured: no paid endpoint latency benchmark or confirmed Monid SLA. | I4: Medium | J4: Ownership tab with filing dates | K4: Historical institution positions are not director/officer transactions or current portfolios. | L4: See P4 source/provenance assessment; Monid authority unverified. | M4: See P4 rights assessment; customer display/storage grant unverified. | N4: Not security-audited. Server-side credentials, endpoint allowlist, input validation and spending caps proposed; no verified Monid SLA or contractual security assurance. | O4: No named customer verified for this exact Monid connector. | P4: Company and institutional-portfolio researchers | Q4: Metadata: T32
A5: T34 | B5: marketbeat | C5: /get_insider_trades | D5: Company insider transactions | E5: Website claim: 20,000 company profiles; Monid/per-tool count unknown. | F5: High auditability with original filing; parsing and transaction interpretation need checks. | G5: Disclosure-lagged; vendor ingestion lag and Monid tier unmeasured. | H5: Unmeasured: no paid endpoint latency benchmark or confirmed Monid SLA. | I5: High | J5: Company insider timeline and holding alerts | K5: Reported transactions need original SEC links, codes and amendment handling. | L5: See P4 source/provenance assessment; Monid authority unverified. | M5: See P4 rights assessment; customer display/storage grant unverified. | N5: Not security-audited. Server-side credentials, endpoint allowlist, input validation and spending caps proposed; no verified Monid SLA or contractual security assurance. | O5: No named customer verified for this exact Monid connector. | P5: Investors studying executive disclosures | Q5: Metadata: T34
A6: T60 | B6: secform4 | C6: /search | D6: Search insider and ownership filings | E6: Unknown company/CIK count; SEC-derived issuer/owner universe. | F6: Useful candidate matching; validate exchange, instrument type and issuer identifiers. | G6: Mostly reference data; newly listed, delisted and renamed securities need updates. | H6: Unmeasured: no paid endpoint latency benchmark or confirmed Monid SLA. | I6: Medium | J6: Insider research search | K6: Search scope and pagination unverified; company and owner identifiers are different. | L6: See P7 source/provenance assessment; Monid authority unverified. | M6: See P7 rights assessment; customer display/storage grant unverified. | N6: Not security-audited. Server-side credentials, endpoint allowlist, input validation and spending caps proposed; no verified Monid SLA or contractual security assurance. | O6: No named customer verified for this exact Monid connector. | P6: Catalogue users and data operations | Q6: Metadata: T60
A7: T61 | B7: secform4 | C7: /get_13d_filings | D7: Activist or significant beneficial-ownership disclosures | E7: Unknown company/CIK count; SEC-derived issuer/owner universe. | F7: Verify original schedule, ownership basis, filer type and amendments. | G7: Disclosure-triggered; not a real-time transaction stream. | H7: Unmeasured: no paid endpoint latency benchmark or confirmed Monid SLA. | I7: High | J7: Ownership-event alerts linked to original filings | K7: 13D is beneficial ownership, not a complete trade tape; filing deadlines differ from Form 4. | L7: See P7 source/provenance assessment; Monid authority unverified. | M7: See P7 rights assessment; customer display/storage grant unverified. | N7: Not security-audited. Server-side credentials, endpoint allowlist, input validation and spending caps proposed; no verified Monid SLA or contractual security assurance. | O7: No named customer verified for this exact Monid connector. | P7: Ownership and event researchers | Q7: Metadata: T61
A8: T62 | B8: secform4 | C8: /get_insider_sales | D8: Reported insider sale list | E8: Unknown company/CIK count; SEC-derived issuer/owner universe. | F8: High auditability with original filing; parsing and transaction interpretation need checks. | G8: Disclosure-lagged; vendor ingestion lag and Monid tier unmeasured. | H8: Unmeasured: no paid endpoint latency benchmark or confirmed Monid SLA. | I8: High | J8: Shared insider-sales feed | K8: Public source module explicitly six months delayed; Monid entitlement and actual freshness unknown. | L8: See P7 source/provenance assessment; Monid authority unverified. | M8: See P7 rights assessment; customer display/storage grant unverified. | N8: Not security-audited. Server-side credentials, endpoint allowlist, input validation and spending caps proposed; no verified Monid SLA or contractual security assurance. | O8: No named customer verified for this exact Monid connector. | P8: Investors studying executive disclosures | Q8: Metadata: T62
A9: T63 | B9: secform4 | C9: /get_significant_insider_buys | D9: Selected large insider purchases | E9: Unknown company/CIK count; SEC-derived issuer/owner universe. | F9: High auditability with original filing; parsing and transaction interpretation need checks. | G9: Disclosure-lagged; vendor ingestion lag and Monid tier unmeasured. | H9: Unmeasured: no paid endpoint latency benchmark or confirmed Monid SLA. | I9: High | J9: Prioritised insider alert queue | K9: Public source six-month delay; vendor selection threshold is not evidence of investment quality. | L9: See P7 source/provenance assessment; Monid authority unverified. | M9: See P7 rights assessment; customer display/storage grant unverified. | N9: Not security-audited. Server-side credentials, endpoint allowlist, input validation and spending caps proposed; no verified Monid SLA or contractual security assurance. | O9: No named customer verified for this exact Monid connector. | P9: Investors studying executive disclosures | Q9: Metadata: T63
A10: T64 | B10: secform4 | C10: /get_institution_holders | D10: Institutional holders of an issuer | E10: Unknown company/CIK count; SEC-derived issuer/owner universe. | F10: Reconcile reporting manager, quarter, security class and amendments. | G10: Periodic, historically reported holdings; not real-time ownership. | H10: Unmeasured: no paid endpoint latency benchmark or confirmed Monid SLA. | I10: Medium | J10: Company ownership history | K10: Reported holdings lag quarter-end; holder population and security class matching matter. | L10: See P7 source/provenance assessment; Monid authority unverified. | M10: See P7 rights assessment; customer display/storage grant unverified. | N10: Not security-audited. Server-side credentials, endpoint allowlist, input validation and spending caps proposed; no verified Monid SLA or contractual security assurance. | O10: No named customer verified for this exact Monid connector. | P10: Company and institutional-portfolio researchers | Q10: Metadata: T64
A11: T65 | B11: secform4 | C11: /get_insider_buy_sell_ratios | D11: Aggregated insider purchase/sale ratios | E11: Unknown company/CIK count; SEC-derived issuer/owner universe. | F11: Validate methodology, source fields and period consistency. | G11: Dependent on underlying source updates and calculation window. | H11: Unmeasured: no paid endpoint latency benchmark or confirmed Monid SLA. | I11: Medium | J11: Labelled insider-activity indicator | K11: Public source six-month delay; ratios depend on transaction types, window and reporting population. | L11: See P7 source/provenance assessment; Monid authority unverified. | M11: See P7 rights assessment; customer display/storage grant unverified. | N11: Not security-audited. Server-side credentials, endpoint allowlist, input validation and spending caps proposed; no verified Monid SLA or contractual security assurance. | O11: No named customer verified for this exact Monid connector. | P11: Investors and company/market researchers | Q11: Metadata: T65
A12: T66 | B12: secform4 | C12: /get_stock_options | D12: Insider option-related transactions | E12: Unknown company/CIK count; SEC-derived issuer/owner universe. | F12: High auditability with original filing; parsing and transaction interpretation need checks. | G12: Disclosure-lagged; vendor ingestion lag and Monid tier unmeasured. | H12: Unmeasured: no paid endpoint latency benchmark or confirmed Monid SLA. | I12: High | J12: Compensation versus cash-purchase explanation | K12: Insider option disclosures, not an exchange option chain; public module six months delayed. | L12: See P7 source/provenance assessment; Monid authority unverified. | M12: See P7 rights assessment; customer display/storage grant unverified. | N12: Not security-audited. Server-side credentials, endpoint allowlist, input validation and spending caps proposed; no verified Monid SLA or contractual security assurance. | O12: No named customer verified for this exact Monid connector. | P12: Investors studying executive disclosures | Q12: Metadata: T66
... A16: T70 | B16: secform4 | C16: /get_13g_filings | D16: Passive or qualified beneficial-ownership disclosures | E16: Unknown company/CIK count; SEC-derived issuer/owner universe. | F16: Verify original schedule, ownership basis, filer type and amendments. | G16: Disclosure-triggered; not a real-time transaction stream. | H16: Unmeasured: no paid endpoint latency benchmark or confirmed Monid SLA. | I16: High | J16: Company ownership notifications | K16: 13G filing cadence depends on filer type and triggering change; not immediate trading activity. | L16: See P7 source/provenance assessment; Monid authority unverified. | M16: See P7 rights assessment; customer display/storage grant unverified. | N16: Not security-audited. Server-side credentials, endpoint allowlist, input validation and spending caps proposed; no verified Monid SLA or contractual security assurance. | O16: No named customer verified for this exact Monid connector. | P16: Ownership and event researchers | Q16: Metadata: T70

Sheet Provider evidence
A1: Code | B1: Provider | C1: Tools | D1: Coverage | E1: Official provenance | F1: Accuracy / quality | G1: Upstream freshness | H1: Permissions / suitability | I1: Audience and adoption distinction | J1: Recommendation | K1: Source URLs
A2: P1 | B2: Nasdaq | C2: 20 | D2: No exact Monid company count verified. Related official feeds cover US exchange-listed securities; each news, fund, options and filing tool can cover a different subset. | E2: Nasdaq is an official exchange operator. Its website also republishes third-party company data and journalism. These Monid listings are not verified as licensed Nasdaq feeds. | F2: Strong potential traceability for exchange data and original filings; mixed confidence for estimates, third-party news and derived fields. No measured connector accuracy. | G2: Website quote bar: three-second refresh; indices at least one minute delayed. Short interest is twice-monthly. Neither establishes Monid delivery latency. The separate official Retail Trading Activity Tracker is daily with a one-day reporting lag. | H2: Nasdaq website terms restrict automated capture and commercial copying, storage and derivative products without consent. A separate licensed feed/distributor agreement is the relevant route; no Monid pass-through grant established. | I2: Retail investors and analysts are the apparent audience. Trading 212 and Microsoft Excel are named users of the separate direct Nasdaq Last Sale product, not these Monid tools. | J2: Conditional research candidate; use an authorised Nasdaq route for critical prices. | K2: https://www.nasdaq.com/products/data/equities/nasdaq-last-sale https://www.nasdaq.com/market-activity/stocks/aapl https://www.nasdaq.com/market-activity https://www.nasdaq.com/market-activity/stocks/aapl/financials https://nasdaqtrader.com/trader.aspx?id=ShortInterest https://data.nasdaq.com/databases/RTAT/documentation?anchor=sample-data https://www.nasdaq.com/legal https://www.nasdaq.com/market-activity/stocks/aapl/institutional-holdings
A3: P2 | B3: Yahoo Finance | C3: 5 | D3: Global exchanges are listed in Yahoo help, but no exact company or news count was verified for Monid. Quote, profile and headline coverage are different questions. | E3: Publisher and secondary financial-data aggregator. Not the original issuer of every article or price record; Monid distribution authority unverified. | F3: Useful international research scope, but adjustments, stale profiles, article duplicates and ticker matching need measurement. No accuracy percentage established. | G3: Exchange dependent: the official table includes real-time Nasdaq, 15-minute OPRA/OTC, 20-minute ASX and 30-minute Shanghai/Shenzhen. Monid adds unmeasured collection/cache lag. | H3: Yahoo Finance help prohibits redistribution of its displayed/provided information. No separate Monid grant was verified. Article and photo rights require their own entitlement. | I3: Suitable for individual investors and analysts (product assessment); no named production customer verified for these Monid endpoints. | J3: On-demand alternative only after rights resolution; comparatively costly for frequent polling. | K3: https://help.yahoo.com/kb/finance/SLN2310.html https://legal.yahoo.com/us/en/yahoo/terms/product-atos/finance/index.html
A4: P3 | B4: Finviz | C4: 5 | D4: The stock-only website screener showed 5,613 ticker rows; the unrestricted version 11,614 including funds. These dynamic observations are not unique companies, insider/news coverage or Monid-supported totals. Source FAQ lists Nasdaq, NYSE and AMEX. | E4: Secondary screener/aggregator. Direct Elite API/export access exists, but the Monid connector is not verified as that authorised product. | F4: Useful screening context, subject to universe/result caps. Sentiment is an interpretation, with no validated model or factual-accuracy score established. | G4: Free website stock quotes are one minute delayed; Elite quotes can be real time; fundamentals refresh hourly. News/insider latency and Monid refresh remain unknown. | H4: Direct API policy is personal-use and prohibits third-party redistribution/resale. Its one-request-per-five-seconds limit is not a verified Monid limit. A personal Elite subscription is not a licence for our app users. | I4: Finviz addresses beginners and professional traders. No named production customer verified for these Monid tools. | J4: Potential screener feature, secondary priority; resolve licence and pagination first. | K4: https://finviz.com/help/faq https://finviz.com/screener?f=ind_stocksonly&v=111 https://finviz.com/screener?v=111 https://finviz.com/knowledge-base/market-data-research/api/usage-limits https://finviz.com/elite
A5: P4 | B5: MarketBeat | C5: 14 | D5: Website advertises 20,000 public-company profiles, with US, Canadian and UK sections. No exact Monid count or assurance that all 14 tools cover all these companies was verified. | E5: Private publisher and aggregator; discloses market-data suppliers and editorial policies. SEC-derived insider tables remain secondary. | F5: Editorial source checks and corrections are positive signals, not a measured endpoint error rate. Some summaries use AI; ratings/forecasts and MarketRank are opinions or models. | G5: Source fair-market-value estimates update each minute; other Barchart market data is at least ten minutes delayed. Model scores, earnings and holdings have different cadences; Monid latency unmeasured. | H5: Terms distinguish personal access, site/XML licences and commercial licensing, and restrict bulk redistribution. No Monid downstream customer-display/storage grant established. | I5: Retail-investor publisher with a large claimed newsletter readership. This is audience evidence, not named Monid API-customer evidence. | J5: One of the more relevant headline/research candidates, conditional on a valid commercial licence. | K5: https://www.marketbeat.com/about/ https://www.marketbeat.com/editorial-guidelines/ https://www.marketbeat.com/faq/ https://www.marketbeat.com/terms/ https://www.marketbeat.com/all-access/insider-trades-screener/
A6: P5 | B6: StockAnalysis | C6: 7 | D6: Website advertises 130,000+ tradable symbols worldwide, including ETFs and multiple listings. This is not a unique-company number or proven Monid coverage. Seven listings were retrievable although eight were advertised. | E6: Secondary research publisher using providers including S&P Global and Fiscal.ai. It explicitly says it has no programmatic API/MCP and lacks programmatic resale rights. | F6: Documented upstream vendors and review practices support manual research. No independent Monid accuracy or completeness benchmark; derived ratios and financial periods need reconciliation. | G6: US website stock pages refresh every five seconds for free users and stream for paid users; source screeners are roughly minute-based; other markets can be delayed or end-of-day. This is not Monid streaming evidence. | H6: Published no-programmatic-access position is a concrete blocker for assuming these are official licensed APIs. A valid, separately evidenced upstream rights chain would be needed before production use. | I6: Regular/individual investors are its stated audience. No named Monid endpoint customers verified. | J6: Hold production integration pending an explanation and proof of lawful programmatic supply. | K6: https://stockanalysis.com/help/data-and-downloads/about-our-data/ https://stockanalysis.com/data-sources/ https://stockanalysis.com/help/faq/stock-price-data/ https://stockanalysis.com/help/faq/api-access/ https://stockanalysis.com/terms-of-use/ https://stockanalysis.com/about/
A7: P6 | B7: DefiLlama equities | C7: 8 | D7: Exact supported company count unverified. Official companies-list returns ticker/country identities to enumerate and match; upstream Twelve Data breadth is not proof of this beta subset. | E7: All eight paths are documented in the vendor’s official Pro API. Equities market/fundamental data is secondary Twelve Data; filing links can lead to primary SEC documents. Monid resale authority remains unverified. | F7: Clearer documented schemas than the web-style wrappers, but beta stability, per-field coverage and source reconciliation need validation. | G7: Beta snapshot/chart service, not a demonstrated tick stream. Short-window charts may use five-minute bars with daily fallback; on-chain venue mappings are hourly. End-to-end lag unmeasured. | H7: DefiLlama API terms and underlying Twelve Data display/redistribution entitlements apply. No confirmed pass-through customer-display grant through Monid. Direct Pro API pricing is a separate purchase route. | I7: Potential audience: equity and crypto researchers. No named adopter of these exact beta equities/Monid endpoints verified. | J7: Best low-cost documented API candidate for a limited fundamentals/chart evaluation, after rights and coverage checks. | K7: https://api-docs.defillama.com/ https://github.com/DefiLlama/api-docs/blob/main/llms-pro.txt https://defillama.com/equities https://defillama.com/terms/ https://twelvedata.com/terms
A8: P7 | B8: SECForm4.com | C8: 11 | D8: No exact company, issuer-CIK or manager count verified for Monid. SEC filing coverage is not a worldwide 50,000-company universe; owner, security and transaction counts are different. | E8: Private SEC-data aggregator, not the SEC. Original accession numbers/documents are needed to establish each record’s provenance. | F8: Potentially highly auditable with originals, but no tested error rate. Amendments, joint reporting, rounded totals and non-split-adjusted shares need handling. | G8: Five public modules disclose a six-month delay: buys, sales, significant buys, insider options and ratios. Company history can be newer. Monid subscription tier and delivered freshness are unverified. | H8: Website subscriptions do not establish a redistribution/API licence. No public grant for Monid customer display, history storage or exports was established. | I8: Investors studying executives and institutions are the intended audience. No named production customer verified for these Monid endpoints. | J8: Do not promise timely insider alerts until tier/lag/rights are proven; prefer official SEC ingestion as the foundation. | K8: https://www.secform4.com/ https://www.secform4.com/all-buys https://www.secform4.com/insider-sales https://www.secform4.com/significant-buys https://www.secform4.com/stock-options https://www.secform4.com/insider-buy-sell-ratios https://www.secform4.com/insider-trading/320193.htm https://www.secform4.com/account/sign-up https://monid.ai/blog/guides/insider-trading-api-form-4-data

Sheet Costs
A1: ID | B1: Provider | C1: Endpoint | D1: Scope | E1: Profile | F1: USD / call | G1: Include? 0/1 | H1: Keys override: 10 | I1: Keys override: 100 | J1: Entities / call | K1: Pages / poll or lookup | L1: Retry overhead | M1: Polls / key / month | N1: Effective keys: 10 | O1: Effective keys: 100 | P1: Research calls: 10 | Q1: Research calls: 100 | R1: Research USD: 10 | S1: Research USD: 100 | T1: Feed calls: 10 | U1: Feed calls: 100 | V1: Feed USD: 10 | W1: Feed USD: 100 | X1: Scope / caveat | Y1: Metadata
A2: T01 | B2: nasdaq | C2: /get_stock_earnings | D2: entity | E2: entity_daily | F2: 0.01 | G2: 0 | H2: 0 | I2: 0 | J2: 1 | K2: 1 | L2: 0 | M2: =Profiles!D7 -> 30 | N2: =IF(H2>0,H2,IF(D2="entity",MAX(Assumptions!$B$7,ROUNDUP(Assumptions!$B$2*Assumptions!$B$7*Assumptions!$B$8,0)),1)) -> 100 | O2: =IF(I2>0,I2,IF(D2="entity",MAX(Assumptions!$B$7,ROUNDUP(Assumptions!$B$3*Assumptions!$B$7*Assumptions!$B$8,0)),1)) -> 1000 | P2: =ROUNDUP(Assumptions!$B$2*Assumptions!$B$4*Assumptions!$B$5/J2,0)*K2*(1+L2) -> 1100 | Q2: =ROUNDUP(Assumptions!$B$3*Assumptions!$B$4*Assumptions!$B$5/J2,0)*K2*(1+L2) -> 11000 | R2: =P2*F2 -> 11 | S2: =Q2*F2 -> 110 | T2: =IF(D2="demand",P2*Assumptions!$B$17,ROUNDUP(N2/J2,0)*M2*K2*(1+L2)) -> 3000 | U2: =IF(D2="demand",Q2*Assumptions!$B$17,ROUNDUP(O2/J2,0)*M2*K2*(1+L2)) -> 30000 | V2: =T2*F2 -> 30 | W2: =U2*F2 -> 300 | X2: One page/query assumed; full coverage and pagination unverified. Shared union of followed keys for entity tools; one shared list for global tools. | Y2: Catalogue price/source
A3: T02 | B3: nasdaq | C3: /get_stock_screener | D3: global | E3: global_market | F3: 0.01 | G3: 0 | H3: 0 | I3: 0 | J3: 1 | K3: 1 | L3: 0 | M3: =Profiles!D3 -> 1716 | N3: =IF(H3>0,H3,IF(D3="entity",MAX(Assumptions!$B$7,ROUNDUP(Assumptions!$B$2*Assumptions!$B$7*Assumptions!$B$8,0)),1)) -> 1 | O3: =IF(I3>0,I3,IF(D3="entity",MAX(Assumptions!$B$7,ROUNDUP(Assumptions!$B$3*Assumptions!$B$7*Assumptions!$B$8,0)),1)) -> 1 | P3: =ROUNDUP(Assumptions!$B$2*Assumptions!$B$4*Assumptions!$B$5/J3,0)*K3*(1+L3) -> 1100 | Q3: =ROUNDUP(Assumptions!$B$3*Assumptions!$B$4*Assumptions!$B$5/J3,0)*K3*(1+L3) -> 11000 | R3: =P3*F3 -> 11 | S3: =Q3*F3 -> 110 | T3: =IF(D3="demand",P3*Assumptions!$B$17,ROUNDUP(N3/J3,0)*M3*K3*(1+L3)) -> 1716 | U3: =IF(D3="demand",Q3*Assumptions!$B$17,ROUNDUP(O3/J3,0)*M3*K3*(1+L3)) -> 1716 | V3: =T3*F3 -> 17.16 | W3: =U3*F3 -> 17.16 | X3: One page/query assumed; full coverage and pagination unverified. Shared union of followed keys for entity tools; one shared list for global tools. | Y3: Catalogue price/source
A4: T03 | B4: nasdaq | C4: /get_earnings_calendar | D4: global | E4: global_daily | F4: 0.01 | G4: 0 | H4: 0 | I4: 0 | J4: 1 | K4: 1 | L4: 0 | M4: =Profiles!D8 -> 30 | N4: =IF(H4>0,H4,IF(D4="entity",MAX(Assumptions!$B$7,ROUNDUP(Assumptions!$B$2*Assumptions!$B$7*Assumptions!$B$8,0)),1)) -> 1 | O4: =IF(I4>0,I4,IF(D4="entity",MAX(Assumptions!$B$7,ROUNDUP(Assumptions!$B$3*Assumptions!$B$7*Assumptions!$B$8,0)),1)) -> 1 | P4: =ROUNDUP(Assumptions!$B$2*Assumptions!$B$4*Assumptions!$B$5/J4,0)*K4*(1+L4) -> 1100 | Q4: =ROUNDUP(Assumptions!$B$3*Assumptions!$B$4*Assumptions!$B$5/J4,0)*K4*(1+L4) -> 11000 | R4: =P4*F4 -> 11 | S4: =Q4*F4 -> 110 | T4: =IF(D4="demand",P4*Assumptions!$B$17,ROUNDUP(N4/J4,0)*M4*K4*(1+L4)) -> 30 | U4: =IF(D4="demand",Q4*Assumptions!$B$17,ROUNDUP(O4/J4,0)*M4*K4*(1+L4)) -> 30 | V4: =T4*F4 -> 0.3 | W4: =U4*F4 -> 0.3 | X4: One page/query assumed; full coverage and pagination unverified. Shared union of followed keys for entity tools; one shared list for global tools. | Y4: Catalogue price/source
A5: T04 | B5: nasdaq | C5: /get_stock_sec_filings | D5: entity | E5: entity_hourly | F5: 0.01 | G5: 0 | H5: 0 | I5: 0 | J5: 1 | K5: 1 | L5: 0 | M5: =Profiles!D5 -> 352 | N5: =IF(H5>0,H5,IF(D5="entity",MAX(Assumptions!$B$7,ROUNDUP(Assumptions!$B$2*Assumptions!$B$7*Assumptions!$B$8,0)),1)) -> 100 | O5: =IF(I5>0,I5,IF(D5="entity",MAX(Assumptions!$B$7,ROUNDUP(Assumptions!$B$3*Assumptions!$B$7*Assumptions!$B$8,0)),1)) -> 1000 | P5: =ROUNDUP(Assumptions!$B$2*Assumptions!$B$4*Assumptions!$B$5/J5,0)*K5*(1+L5) -> 1100 | Q5: =ROUNDUP(Assumptions!$B$3*Assumptions!$B$4*Assumptions!$B$5/J5,0)*K5*(1+L5) -> 11000 | R5: =P5*F5 -> 11 | S5: =Q5*F5 -> 110 | T5: =IF(D5="demand",P5*Assumptions!$B$17,ROUNDUP(N5/J5,0)*M5*K5*(1+L5)) -> 35200 | U5: =IF(D5="demand",Q5*Assumptions!$B$17,ROUNDUP(O5/J5,0)*M5*K5*(1+L5)) -> 352000 | V5: =T5*F5 -> 352 | W5: =U5*F5 -> 3520 | X5: One page/query assumed; full coverage and pagination unverified. Shared union of followed keys for entity tools; one shared list for global tools. | Y5: Catalogue price/source
A6: T05 | B6: nasdaq | C6: /get_mutual_fund_quote | D6: entity | E6: entity_daily | F6: 0.01 | G6: 0 | H6: 5 | I6: 5 | J6: 1 | K6: 1 | L6: 0 | M6: =Profiles!D7 -> 30 | N6: =IF(H6>0,H6,IF(D6="entity",MAX(Assumptions!$B$7,ROUNDUP(Assumptions!$B$2*Assumptions!$B$7*Assumptions!$B$8,0)),1)) -> 5 | O6: =IF(I6>0,I6,IF(D6="entity",MAX(Assumptions!$B$7,ROUNDUP(Assumptions!$B$3*Assumptions!$B$7*Assumptions!$B$8,0)),1)) -> 5 | P6: =ROUNDUP(Assumptions!$B$2*Assumptions!$B$4*Assumptions!$B$5/J6,0)*K6*(1+L6) -> 1100 | Q6: =ROUNDUP(Assumptions!$B$3*Assumptions!$B$4*Assumptions!$B$5/J6,0)*K6*(1+L6) -> 11000 | R6: =P6*F6 -> 11 | S6: =Q6*F6 -> 110 | T6: =IF(D6="demand",P6*Assumptions!$B$17,ROUNDUP(N6/J6,0)*M6*K6*(1+L6)) -> 150 | U6: =IF(D6="demand",Q6*Assumptions!$B$17,ROUNDUP(O6/J6,0)*M6*K6*(1+L6)) -> 150 | V6: =T6*F6 -> 1.5 | W6: =U6*F6 -> 1.5 | X6: One page/query assumed; full coverage and pagination unverified. Fixed optional universe of 5 keys in both scenarios. | Y6: Catalogue price/source
A7: T06 | B7: nasdaq | C7: /get_stock_dividend_history | D7: entity | E7: entity_daily | F7: 0.01 | G7: 0 | H7: 0 | I7: 0 | J7: 1 | K7: 1 | L7: 0 | M7: =Profiles!D7 -> 30 | N7: =IF(H7>0,H7,IF(D7="entity",MAX(Assumptions!$B$7,ROUNDUP(Assumptions!$B$2*Assumptions!$B$7*Assumptions!$B$8,0)),1)) -> 100 | O7: =IF(I7>0,I7,IF(D7="entity",MAX(Assumptions!$B$7,ROUNDUP(Assumptions!$B$3*Assumptions!$B$7*Assumptions!$B$8,0)),1)) -> 1000 | P7: =ROUNDUP(Assumptions!$B$2*Assumptions!$B$4*Assumptions!$B$5/J7,0)*K7*(1+L7) -> 1100 | Q7: =ROUNDUP(Assumptions!$B$3*Assumptions!$B$4*Assumptions!$B$5/J7,0)*K7*(1+L7) -> 11000 | R7: =P7*F7 -> 11 | S7: =Q7*F7 -> 110 | T7: =IF(D7="demand",P7*Assumptions!$B$17,ROUNDUP(N7/J7,0)*M7*K7*(1+L7)) -> 3000 | U7: =IF(D7="demand",Q7*Assumptions!$B$17,ROUNDUP(O7/J7,0)*M7*K7*(1+L7)) -> 30000 | V7: =T7*F7 -> 30 | W7: =U7*F7 -> 300 | X7: One page/query assumed; full coverage and pagination unverified. Shared union of followed keys for entity tools; one shared list for global tools. | Y7: Catalogue price/source
A8: T07 | B8: nasdaq | C8: /get_stock_quote | D8: entity | E8: entity_market | F8: 0.01 | G8: 0 | H8: 0 | I8: 0 | J8: 1 | K8: 1 | L8: 0 | M8: =Profiles!D2 -> 1716 | N8: =IF(H8>0,H8,IF(D8="entity",MAX(Assumptions!$B$7,ROUNDUP(Assumptions!$B$2*Assumptions!$B$7*Assumptions!$B$8,0)),1)) -> 100 | O8: =IF(I8>0,I8,IF(D8="entity",MAX(Assumptions!$B$7,ROUNDUP(Assumptions!$B$3*Assumptions!$B$7*Assumptions!$B$8,0)),1)) -> 1000 | P8: =ROUNDUP(Assumptions!$B$2*Assumptions!$B$4*Assumptions!$B$5/J8,0)*K8*(1+L8) -> 1100 | Q8: =ROUNDUP(Assumptions!$B$3*Assumptions!$B$4*Assumptions!$B$5/J8,0)*K8*(1+L8) -> 11000 | R8: =P8*F8 -> 11 | S8: =Q8*F8 -> 110 | T8: =IF(D8="demand",P8*Assumptions!$B$17,ROUNDUP(N8/J8,0)*M8*K8*(1+L8)) -> 171600 | U8: =IF(D8="demand",Q8*Assumptions!$B$17,ROUNDUP(O8/J8,0)*M8*K8*(1+L8)) -> 1716000 | V8: =T8*F8 -> 1716 | W8: =U8*F8 -> 17160 | X8: One page/query assumed; full coverage and pagination unverified. Shared union of followed keys for entity tools; one shared list for global tools. | Y8: Catalogue price/source
A9: T08 | B9: nasdaq | C9: /search_symbols | D9: demand | E9: lookup_demand | F9: 0.01 | G9: 0 | H9: 0 | I9: 0 | J9: 1 | K9: 1 | L9: 0 | M9: =Profiles!D9 -> 0 | N9: =IF(H9>0,H9,IF(D9="entity",MAX(Assumptions!$B$7,ROUNDUP(Assumptions!$B$2*Assumptions!$B$7*Assumptions!$B$8,0)),1)) -> 1 | O9: =IF(I9>0,I9,IF(D9="entity",MAX(Assumptions!$B$7,ROUNDUP(Assumptions!$B$3*Assumptions!$B$7*Assumptions!$B$8,0)),1)) -> 1 | P9: =ROUNDUP(Assumptions!$B$2*Assumptions!$B$4*Assumptions!$B$5/J9,0)*K9*(1+L9) -> 1100 | Q9: =ROUNDUP(Assumptions!$B$3*Assumptions!$B$4*Assumptions!$B$5/J9,0)*K9*(1+L9) -> 11000 | R9: =P9*F9 -> 11 | S9: =Q9*F9 -> 110 | T9: =IF(D9="demand",P9*Assumptions!$B$17,ROUNDUP(N9/J9,0)*M9*K9*(1+L9)) -> 550 | U9: =IF(D9="demand",Q9*Assumptions!$B$17,ROUNDUP(O9/J9,0)*M9*K9*(1+L9)) -> 5500 | V9: =T9*F9 -> 5.5 | W9: =U9*F9 -> 55 | X9: One page/query assumed; full coverage and pagination unverified. Shared union of followed keys for entity tools; one shared list for global tools. | Y9: Catalogue price/source
A10: T09 | B10: nasdaq | C10: /get_market_indices | D10: global | E10: global_market | F10: 0.01 | G10: 0 | H10: 0 | I10: 0 | J10: 1 | K10: 1 | L10: 0 | M10: =Profiles!D3 -> 1716 | N10: =IF(H10>0,H10,IF(D10="entity",MAX(Assumptions!$B$7,ROUNDUP(Assumptions!$B$2*Assumptions!$B$7*Assumptions!$B$8,0)),1)) -> 1 | O10: =IF(I10>0,I10,IF(D10="entity",MAX(Assumptions!$B$7,ROUNDUP(Assumptions!$B$3*Assumptions!$B$7*Assumptions!$B$8,0)),1)) -> 1 | P10: =ROUNDUP(Assumptions!$B$2*Assumptions!$B$4*Assumptions!$B$5/J10,0)*K10*(1+L10) -> 1100 | Q10: =ROUNDUP(Assumptions!$B$3*Assumptions!$B$4*Assumptions!$B$5/J10,0)*K10*(1+L10) -> 11000 | R10: =P10*F10 -> 11 | S10: =Q10*F10 -> 110 | T10: =IF(D10="demand",P10*Assumptions!$B$17,ROUNDUP(N10/J10,0)*M10*K10*(1+L10)) -> 1716 | U10: =IF(D10="demand",Q10*Assumptions!$B$17,ROUNDUP(O10/J10,0)*M10*K10*(1+L10)) -> 1716 | V10: =T10*F10 -> 17.16 | W10: =U10*F10 -> 17.16 | X10: One page/query assumed; full coverage and pagination unverified. Shared union of followed keys for entity tools; one shared list for global tools. | Y10: Catalogue price/source
A11: T10 | B11: nasdaq | C11: /get_stock_historical_quotes | D11: entity | E11: entity_daily | F11: 0.01 | G11: 0 | H11: 0 | I11: 0 | J11: 1 | K11: 1 | L11: 0 | M11: =Profiles!D7 -> 30 | N11: =IF(H11>0,H11,IF(D11="entity",MAX(Assumptions!$B$7,ROUNDUP(Assumptions!$B$2*Assumptions!$B$7*Assumptions!$B$8,0)),1)) -> 100 | O11: =IF(I11>0,I11,IF(D11="entity",MAX(Assumptions!$B$7,ROUNDUP(Assumptions!$B$3*Assumptions!$B$7*Assumptions!$B$8,0)),1)) -> 1000 | P11: =ROUNDUP(Assumptions!$B$2*Assumptions!$B$4*Assumptions!$B$5/J11,0)*K11*(1+L11) -> 1100 | Q11: =ROUNDUP(Assumptions!$B$3*Assumptions!$B$4*Assumptions!$B$5/J11,0)*K11*(1+L11) -> 11000 | R11: =P11*F11 -> 11 | S11: =Q11*F11 -> 110 | T11: =IF(D11="demand",P11*Assumptions!$B$17,ROUNDUP(N11/J11,0)*M11*K11*(1+L11)) -> 3000 | U11: =IF(D11="demand",Q11*Assumptions!$B$17,ROUNDUP(O11/J11,0)*M11*K11*(1+L11)) -> 30000 | V11: =T11*F11 -> 30 | W11: =U11*F11 -> 300 | X11: One page/query assumed; full coverage and pagination unverified. Shared union of followed keys for entity tools; one shared list for global tools. | Y11: Catalogue price/source
A12: T11 | B12: nasdaq | C12: /get_stock_institutional_holdings | D12: entity | E12: entity_daily | F12: 0.01 | G12: 0 | H12: 0 | I12: 0 | J12: 1 | K12: 1 | L12: 0 | M12: =Profiles!D7 -> 30 | N12: =IF(H12>0,H12,IF(D12="entity",MAX(Assumptions!$B$7,ROUNDUP(Assumptions!$B$2*Assumptions!$B$7*Assumptions!$B$8,0)),1)) -> 100 | O12: =IF(I12>0,I12,IF(D12="entity",MAX(Assumptions!$B$7,ROUNDUP(Assumptions!$B$3*Assumptions!$B$7*Assumptions!$B$8,0)),1)) -> 1000 | P12: =ROUNDUP(Assumptions!$B$2*Assumptions!$B$4*Assumptions!$B$5/J12,0)*K12*(1+L12) -> 1100 | Q12: =ROUNDUP(Assumptions!$B$3*Assumptions!$B$4*Assumptions!$B$5/J12,0)*K12*(1+L12) -> 11000 | R12: =P12*F12 -> 11 | S12: =Q12*F12 -> 110 | T12: =IF(D12="demand",P12*Assumptions!$B$17,ROUNDUP(N12/J12,0)*M12*K12*(1+L12)) -> 3000 | U12: =IF(D12="demand",Q12*Assumptions!$B$17,ROUNDUP(O12/J12,0)*M12*K12*(1+L12)) -> 30000 | V12: =T12*F12 -> 30 | W12: =U12*F12 -> 300 | X12: One page/query assumed; full coverage and pagination unverified. Shared union of followed keys for entity tools; one shared list for global tools. | Y12: Catalogue price/source
A13: T12 | B13: nasdaq | C13: /get_market_movers | D13: global | E13: global_market | F13: 0.01 | G13: 0 | H13: 0 | I13: 0 | J13: 1 | K13: 1 | L13: 0 | M13: =Profiles!D3 -> 1716 | N13: =IF(H13>0,H13,IF(D13="entity",MAX(Assumptions!$B$7,ROUNDUP(Assumptions!$B$2*Assumptions!$B$7*Assumptions!$B$8,0)),1)) -> 1 | O13: =IF(I13>0,I13,IF(D13="entity",MAX(Assumptions!$B$7,ROUNDUP(Assumptions!$B$3*Assumptions!$B$7*Assumptions!$B$8,0)),1)) -> 1 | P13: =ROUNDUP(Assumptions!$B$2*Assumptions!$B$4*Assumptions!$B$5/J13,0)*K13*(1+L13) -> 1100 | Q13: =ROUNDUP(Assumptions!$B$3*Assumptions!$B$4*Assumptions!$B$5/J13,0)*K13*(1+L13) -> 11000 | R13: =P13*F13 -> 11 | S13: =Q13*F13 -> 110 | T13: =IF(D13="demand",P13*Assumptions!$B$17,ROUNDUP(N13/J13,0)*M13*K13*(1+L13)) -> 1716 | U13: =IF(D13="demand",Q13*Assumptions!$B$17,ROUNDUP(O13/J13,0)*M13*K13*(1+L13)) -> 1716 | V13: =T13*F13 -> 17.16 | W13: =U13*F13 -> 17.16 | X13: One page/query assumed; full coverage and pagination unverified. Shared union of followed keys for entity tools; one shared list for global tools. | Y13: Catalogue price/source
A14: T13 | B14: nasdaq | C14: /get_etf_quote | D14: entity | E14: entity_market | F14: 0.01 | G14: 0 | H14: 5 | I14: 5 | J14: 1 | K14: 1 | L14: 0 | M14: =Profiles!D2 -> 1716 | N14: =IF(H14>0,H14,IF(D14="entity",MAX(Assumptions!$B$7,ROUNDUP(Assumptions!$B$2*Assumptions!$B$7*Assumptions!$B$8,0)),1)) -> 5 | O14: =IF(I14>0,I14,IF(D14="entity",MAX(Assumptions!$B$7,ROUNDUP(Assumptions!$B$3*Assumptions!$B$7*Assumptions!$B$8,0)),1)) -> 5 | P14: =ROUNDUP(Assumptions!$B$2*Assumptions!$B$4*Assumptions!$B$5/J14,0)*K14*(1+L14) -> 1100 | Q14: =ROUNDUP(Assumptions!$B$3*Assumptions!$B$4*Assumptions!$B$5/J14,0)*K14*(1+L14) -> 11000 | R14: =P14*F14 -> 11 | S14: =Q14*F14 -> 110 | T14: =IF(D14="demand",P14*Assumptions!$B$17,ROUNDUP(N14/J14,0)*M14*K14*(1+L14)) -> 8580 | U14: =IF(D14="demand",Q14*Assumptions!$B$17,ROUNDUP(O14/J14,0)*M14*K14*(1+L14)) -> 8580 | V14: =T14*F14 -> 85.8 | W14: =U14*F14 -> 85.8 | X14: One page/query assumed; full coverage and pagination unverified. Fixed optional universe of 5 keys in both scenarios. | Y14: Catalogue price/source
A15: T14 | B15: nasdaq | C15: /get_cryptocurrency_quote | D15: entity | E15: entity_crypto | F15: 0.01 | G15: 0 | H15: 2 | I15: 2 | J15: 1 | K15: 1 | L15: 0 | M15: =Profiles!D10 -> 8640 | N15: =IF(H15>0,H15,IF(D15="entity",MAX(Assumptions!$B$7,ROUNDUP(Assumptions!$B$2*Assumptions!$B$7*Assumptions!$B$8,0)),1)) -> 2 | O15: =IF(I15>0,I15,IF(D15="entity",MAX(Assumptions!$B$7,ROUNDUP(Assumptions!$B$3*Assumptions!$B$7*Assumptions!$B$8,0)),1)) -> 2 | P15: =ROUNDUP(Assumptions!$B$2*Assumptions!$B$4*Assumptions!$B$5/J15,0)*K15*(1+L15) -> 1100 | Q15: =ROUNDUP(Assumptions!$B$3*Assumptions!$B$4*Assumptions!$B$5/J15,0)*K15*(1+L15) -> 11000 | R15: =P15*F15 -> 11 | S15: =Q15*F15 -> 110 | T15: =IF(D15="demand",P15*Assumptions!$B$17,ROUNDUP(N15/J15,0)*M15*K15*(1+L15)) -> 17280 | U15: =IF(D15="demand",Q15*Assumptions!$B$17,ROUNDUP(O15/J15,0)*M15*K15*(1+L15)) -> 17280 | V15: =T15*F15 -> 172.8 | W15: =U15*F15 -> 172.8 | X15: One page/query assumed; full coverage and pagination unverified. Fixed optional universe of 2 keys in both scenarios. | Y15: Catalogue price/source
A16: T15 | B16: nasdaq | C16: /get_stock_news | D16: entity | E16: entity_news | F16: 0.01 | G16: 0 | H16: 0 | I16: 0 | J16: 1 | K16: 1 | L16: 0 | M16: =Profiles!D4 -> 480 | N16: =IF(H16>0,H16,IF(D16="entity",MAX(Assumptions!$B$7,ROUNDUP(Assumptions!$B$2*Assumptions!$B$7*Assumptions!$B$8,0)),1)) -> 100 | O16: =IF(I16>0,I16,IF(D16="entity",MAX(Assumptions!$B$7,ROUNDUP(Assumptions!$B$3*Assumptions!$B$7*Assumptions!$B$8,0)),1)) -> 1000 | P16: =ROUNDUP(Assumptions!$B$2*Assumptions!$B$4*Assumptions!$B$5/J16,0)*K16*(1+L16) -> 1100 | Q16: =ROUNDUP(Assumptions!$B$3*Assumptions!$B$4*Assumptions!$B$5/J16,0)*K16*(1+L16) -> 11000 | R16: =P16*F16 -> 11 | S16: =Q16*F16 -> 110 | T16: =IF(D16="demand",P16*Assumptions!$B$17,ROUNDUP(N16/J16,0)*M16*K16*(1+L16)) -> 48000 | U16: =IF(D16="demand",Q16*Assumptions!$B$17,ROUNDUP(O16/J16,0)*M16*K16*(1+L16)) -> 480000 | V16: =T16*F16 -> 480 | W16: =U16*F16 -> 4800 | X16: One page/query assumed; full coverage and pagination unverified. Shared union of followed keys for entity tools; one shared list for global tools. | Y16: Catalogue price/source
A17: T16 | B17: nasdaq | C17: /get_stock_financials | D17: entity | E17: entity_daily | F17: 0.01 | G17: 0 | H17: 0 | I17: 0 | J17: 1 | K17: 1 | L17: 0 | M17: =Profiles!D7 -> 30 | N17: =IF(H17>0,H17,IF(D17="entity",MAX(Assumptions!$B$7,ROUNDUP(Assumptions!$B$2*Assumptions!$B$7*Assumptions!$B$8,0)),1)) -> 100 | O17: =IF(I17>0,I17,IF(D17="entity",MAX(Assumptions!$B$7,ROUNDUP(Assumptions!$B$3*Assumptions!$B$7*Assumptions!$B$8,0)),1)) -> 1000 | P17: =ROUNDUP(Assumptions!$B$2*Assumptions!$B$4*Assumptions!$B$5/J17,0)*K17*(1+L17) -> 1100 | Q17: =ROUNDUP(Assumptions!$B$3*Assumptions!$B$4*Assumptions!$B$5/J17,0)*K17*(1+L17) -> 11000 | R17: =P17*F17 -> 11 | S17: =Q17*F17 -> 110 | T17: =IF(D17="demand",P17*Assumptions!$B$17,ROUNDUP(N17/J17,0)*M17*K17*(1+L17)) -> 3000 | U17: =IF(D17="demand",Q17*Assumptions!$B$17,ROUNDUP(O17/J17,0)*M17*K17*(1+L17)) -> 30000 | V17: =T17*F17 -> 30 | W17: =U17*F17 -> 300 | X17: One page/query assumed; full coverage and pagination unverified. Shared union of followed keys for entity tools; one shared list for global tools. | Y17: Catalogue price/source
A18: T17 | B18: nasdaq | C18: /get_index_detail | D18: entity | E18: entity_market | F18: 0.01 | G18: 0 | H18: 5 | I18: 5 | J18: 1 | K18: 1 | L18: 0 | M18: =Profiles!D2 -> 1716 | N18: =IF(H18>0,H18,IF(D18="entity",MAX(Assumptions!$B$7,ROUNDUP(Assumptions!$B$2*Assumptions!$B$7*Assumptions!$B$8,0)),1)) -> 5 | O18: =IF(I18>0,I18,IF(D18="entity",MAX(Assumptions!$B$7,ROUNDUP(Assumptions!$B$3*Assumptions!$B$7*Assumptions!$B$8,0)),1)) -> 5 | P18: =ROUNDUP(Assumptions!$B$2*Assumptions!$B$4*Assumptions!$B$5/J18,0)*K18*(1+L18) -> 1100 | Q18: =ROUNDUP(Assumptions!$B$3*Assumptions!$B$4*Assumptions!$B$5/J18,0)*K18*(1+L18) -> 11000 | R18: =P18*F18 -> 11 | S18: =Q18*F18 -> 110 | T18: =IF(D18="demand",P18*Assumptions!$B$17,ROUNDUP(N18/J18,0)*M18*K18*(1+L18)) -> 8580 | U18: =IF(D18="demand",Q18*Assumptions!$B$17,ROUNDUP(O18/J18,0)*M18*K18*(1+L18)) -> 8580 | V18: =T18*F18 -> 85.8 | W18: =U18*F18 -> 85.8 | X18: One page/query assumed; full coverage and pagination unverified. Fixed optional universe of 5 keys in both scenarios. | Y18: Catalogue price/source
A19: T18 | B19: nasdaq | C19: /get_stock_short_interest | D19: entity | E19: entity_daily | F19: 0.01 | G19: 0 | H19: 0 | I19: 0 | J19: 1 | K19: 1 | L19: 0 | M19: =Profiles!D7 -> 30 | N19: =IF(H19>0,H19,IF(D19="entity",MAX(Assumptions!$B$7,ROUNDUP(Assumptions!$B$2*Assumptions!$B$7*Assumptions!$B$8,0)),1)) -> 100 | O19: =IF(I19>0,I19,IF(D19="entity",MAX(Assumptions!$B$7,ROUNDUP(Assumptions!$B$3*Assumptions!$B$7*Assumptions!$B$8,0)),1)) -> 1000 | P19: =ROUNDUP(Assumptions!$B$2*Assumptions!$B$4*Assumptions!$B$5/J19,0)*K19*(1+L19) -> 1100 | Q19: =ROUNDUP(Assumptions!$B$3*Assumptions!$B$4*Assumptions!$B$5/J19,0)*K19*(1+L19) -> 11000 | R19: =P19*F19 -> 11 | S19: =Q19*F19 -> 110 | T19: =IF(D19="demand",P19*Assumptions!$B$17,ROUNDUP(N19/J19,0)*M19*K19*(1+L19)) -> 3000 | U19: =IF(D19="demand",Q19*Assumptions!$B$17,ROUNDUP(O19/J19,0)*M19*K19*(1+L19)) -> 30000 | V19: =T19*F19 -> 30 | W19: =U19*F19 -> 300 | X19: One page/query assumed; full coverage and pagination unverified. Shared union of followed keys for entity tools; one shared list for global tools. | Y19: Catalogue price/source
A20: T19 | B20: nasdaq | C20: /get_stock_option_chain | D20: entity | E20: entity_market | F20: 0.01 | G20: 0 | H20: 0 | I20: 0 | J20: 1 | K20: 1 | L20: 0 | M20: =Profiles!D2 -> 1716 | N20: =IF(H20>0,H20,IF(D20="entity",MAX(Assumptions!$B$7,ROUNDUP(Assumptions!$B$2*Assumptions!$B$7*Assumptions!$B$8,0)),1)) -> 100 | O20: =IF(I20>0,I20,IF(D20="entity",MAX(Assumptions!$B$7,ROUNDUP(Assumptions!$B$3*Assumptions!$B$7*Assumptions!$B$8,0)),1)) -> 1000 | P20: =ROUNDUP(Assumptions!$B$2*Assumptions!$B$4*Assumptions!$B$5/J20,0)*K20*(1+L20) -> 1100 | Q20: =ROUNDUP(Assumptions!$B$3*Assumptions!$B$4*Assumptions!$B$5/J20,0)*K20*(1+L20) -> 11000 | R20: =P20*F20 -> 11 | S20: =Q20*F20 -> 110 | T20: =IF(D20="demand",P20*Assumptions!$B$17,ROUNDUP(N20/J20,0)*M20*K20*(1+L20)) -> 171600 | U20: =IF(D20="demand",Q20*Assumptions!$B$17,ROUNDUP(O20/J20,0)*M20*K20*(1+L20)) -> 1716000 | V20: =T20*F20 -> 1716 | W20: =U20*F20 -> 17160 | X20: One page/query assumed; full coverage and pagination unverified. Shared union of followed keys for entity tools; one shared list for global tools. | Y20: Catalogue price/source
A21: T20 | B21: nasdaq | C21: /get_retail_trading_activity | D21: global | E21: global_daily | F21: 0.01 | G21: 0 | H21: 0 | I21: 0 | J21: 1 | K21: 1 | L21: 0 | M21: =Profiles!D8 -> 30 | N21: =IF(H21>0,H21,IF(D21="entity",MAX(Assumptions!$B$7,ROUNDUP(Assumptions!$B$2*Assumptions!$B$7*Assumptions!$B$8,0)),1)) -> 1 | O21: =IF(I21>0,I21,IF(D21="entity",MAX(Assumptions!$B$7,ROUNDUP(Assumptions!$B$3*Assumptions!$B$7*Assumptions!$B$8,0)),1)) -> 1 | P21: =ROUNDUP(Assumptions!$B$2*Assumptions!$B$4*Assumptions!$B$5/J21,0)*K21*(1+L21) -> 1100 | Q21: =ROUNDUP(Assumptions!$B$3*Assumptions!$B$4*Assumptions!$B$5/J21,0)*K21*(1+L21) -> 11000 | R21: =P21*F21 -> 11 | S21: =Q21*F21 -> 110 | T21: =IF(D21="demand",P21*Assumptions!$B$17,ROUNDUP(N21/J21,0)*M21*K21*(1+L21)) -> 30 | U21: =IF(D21="demand",Q21*Assumptions!$B$17,ROUNDUP(O21/J21,0)*M21*K21*(1+L21)) -> 30 | V21: =T21*F21 -> 0.3 | W21: =U21*F21 -> 0.3 | X21: One page/query assumed; full coverage and pagination unverified. Shared union of followed keys for entity tools; one shared list for global tools. | Y21: Catalogue price/source
A22: T21 | B22: yahoo-finance | C22: /get_historical_data | D22: entity | E22: entity_daily | F22: 0.05 | G22: 0 | H22: 0 | I22: 0 | J22: 1 | K22: 1 | L22: 0 | M22: =Profiles!D7 -> 30 | N22: =IF(H22>0,H22,IF(D22="entity",MAX(Assumptions!$B$7,ROUNDUP(Assumptions!$B$2*Assumptions!$B$7*Assumptions!$B$8,0)),1)) -> 100 | O22: =IF(I22>0,I22,IF(D22="entity",MAX(Assumptions!$B$7,ROUNDUP(Assumptions!$B$3*Assumptions!$B$7*Assumptions!$B$8,0)),1)) -> 1000 | P22: =ROUNDUP(Assumptions!$B$2*Assumptions!$B$4*Assumptions!$B$5/J22,0)*K22*(1+L22) -> 1100 | Q22: =ROUNDUP(Assumptions!$B$3*Assumptions!$B$4*Assumptions!$B$5/J22,0)*K22*(1+L22) -> 11000 | R22: =P22*F22 -> 55 | S22: =Q22*F22 -> 550 | T22: =IF(D22="demand",P22*Assumptions!$B$17,ROUNDUP(N22/J22,0)*M22*K22*(1+L22)) -> 3000 | U22: =IF(D22="demand",Q22*Assumptions!$B$17,ROUNDUP(O22/J22,0)*M22*K22*(1+L22)) -> 30000 | V22: =T22*F22 -> 150 | W22: =U22*F22 -> 1500 | X22: One page/query assumed; full coverage and pagination unverified. Shared union of followed keys for entity tools; one shared list for global tools. | Y22: Catalogue price/source
A23: T22 | B23: yahoo-finance | C23: /get_company_profile | D23: entity | E23: entity_daily | F23: 0.05 | G23: 0 | H23: 0 | I23: 0 | J23: 1 | K23: 1 | L23: 0 | M23: =Profiles!D7 -> 30 | N23: =IF(H23>0,H23,IF(D23="entity",MAX(Assumptions!$B$7,ROUNDUP(Assumptions!$B$2*Assumptions!$B$7*Assumptions!$B$8,0)),1)) -> 100 | O23: =IF(I23>0,I23,IF(D23="entity",MAX(Assumptions!$B$7,ROUNDUP(Assumptions!$B$3*Assumptions!$B$7*Assumptions!$B$8,0)),1)) -> 1000 | P23: =ROUNDUP(Assumptions!$B$2*Assumptions!$B$4*Assumptions!$B$5/J23,0)*K23*(1+L23) -> 1100 | Q23: =ROUNDUP(Assumptions!$B$3*Assumptions!$B$4*Assumptions!$B$5/J23,0)*K23*(1+L23) -> 11000 | R23: =P23*F23 -> 55 | S23: =Q23*F23 -> 550 | T23: =IF(D23="demand",P23*Assumptions!$B$17,ROUNDUP(N23/J23,0)*M23*K23*(1+L23)) -> 3000 | U23: =IF(D23="demand",Q23*Assumptions!$B$17,ROUNDUP(O23/J23,0)*M23*K23*(1+L23)) -> 30000 | V23: =T23*F23 -> 150 | W23: =U23*F23 -> 1500 | X23: One page/query assumed; full coverage and pagination unverified. Shared union of followed keys for entity tools; one shared list for global tools. | Y23: Catalogue price/source
A24: T23 | B24: yahoo-finance | C24: /get_stock_news | D24: entity | E24: entity_news | F24: 0.05 | G24: 0 | H24: 0 | I24: 0 | J24: 1 | K24: 1 | L24: 0 | M24: =Profiles!D4 -> 480 | N24: =IF(H24>0,H24,IF(D24="entity",MAX(Assumptions!$B$7,ROUNDUP(Assumptions!$B$2*Assumptions!$B$7*Assumptions!$B$8,0)),1)) -> 100 | O24: =IF(I24>0,I24,IF(D24="entity",MAX(Assumptions!$B$7,ROUNDUP(Assumptions!$B$3*Assumptions!$B$7*Assumptions!$B$8,0)),1)) -> 1000 | P24: =ROUNDUP(Assumptions!$B$2*Assumptions!$B$4*Assumptions!$B$5/J24,0)*K24*(1+L24) -> 1100 | Q24: =ROUNDUP(Assumptions!$B$3*Assumptions!$B$4*Assumptions!$B$5/J24,0)*K24*(1+L24) -> 11000 | R24: =P24*F24 -> 55 | S24: =Q24*F24 -> 550 | T24: =IF(D24="demand",P24*Assumptions!$B$17,ROUNDUP(N24/J24,0)*M24*K24*(1+L24)) -> 48000 | U24: =IF(D24="demand",Q24*Assumptions!$B$17,ROUNDUP(O24/J24,0)*M24*K24*(1+L24)) -> 480000 | V24: =T24*F24 -> 2400 | W24: =U24*F24 -> 24000 | X24: One page/query assumed; full coverage and pagination unverified. Shared union of followed keys for entity tools; one shared list for global tools. | Y24: Catalogue price/source
A25: T24 | B25: yahoo-finance | C25: /get_quote | D25: entity | E25: entity_market | F25: 0.05 | G25: 0 | H25: 0 | I25: 0 | J25: 1 | K25: 1 | L25: 0 | M25: =Profiles!D2 -> 1716 | N25: =IF(H25>0,H25,IF(D25="entity",MAX(Assumptions!$B$7,ROUNDUP(Assumptions!$B$2*Assumptions!$B$7*Assumptions!$B$8,0)),1)) -> 100 | O25: =IF(I25>0,I25,IF(D25="entity",MAX(Assumptions!$B$7,ROUNDUP(Assumptions!$B$3*Assumptions!$B$7*Assumptions!$B$8,0)),1)) -> 1000 | P25: =ROUNDUP(Assumptions!$B$2*Assumptions!$B$4*Assumptions!$B$5/J25,0)*K25*(1+L25) -> 1100 | Q25: =ROUNDUP(Assumptions!$B$3*Assumptions!$B$4*Assumptions!$B$5/J25,0)*K25*(1+L25) -> 11000 | R25: =P25*F25 -> 55 | S25: =Q25*F25 -> 550 | T25: =IF(D25="demand",P25*Assumptions!$B$17,ROUNDUP(N25/J25,0)*M25*K25*(1+L25)) -> 171600 | U25: =IF(D25="demand",Q25*Assumptions!$B$17,ROUNDUP(O25/J25,0)*M25*K25*(1+L25)) -> 1716000 | V25: =T25*F25 -> 8580 | W25: =U25*F25 -> 85800 | X25: One page/query assumed; full coverage and pagination unverified. Shared union of followed keys for entity tools; one shared list for global tools. | Y25: Catalogue price/source
A26: T25 | B26: yahoo-finance | C26: /search_tickers | D26: demand | E26: lookup_demand | F26: 0.05 | G26: 0 | H26: 0 | I26: 0 | J26: 1 | K26: 1 | L26: 0 | M26: =Profiles!D9 -> 0 | N26: =IF(H26>0,H26,IF(D26="entity",MAX(Assumptions!$B$7,ROUNDUP(Assumptions!$B$2*Assumptions!$B$7*Assumptions!$B$8,0)),1)) -> 1 | O26: =IF(I26>0,I26,IF(D26="entity",MAX(Assumptions!$B$7,ROUNDUP(Assumptions!$B$3*Assumptions!$B$7*Assumptions!$B$8,0)),1)) -> 1 | P26: =ROUNDUP(Assumptions!$B$2*Assumptions!$B$4*Assumptions!$B$5/J26,0)*K26*(1+L26) -> 1100 | Q26: =ROUNDUP(Assumptions!$B$3*Assumptions!$B$4*Assumptions!$B$5/J26,0)*K26*(1+L26) -> 11000 | R26: =P26*F26 -> 55 | S26: =Q26*F26 -> 550 | T26: =IF(D26="demand",P26*Assumptions!$B$17,ROUNDUP(N26/J26,0)*M26*K26*(1+L26)) -> 550 | U26: =IF(D26="demand",Q26*Assumptions!$B$17,ROUNDUP(O26/J26,0)*M26*K26*(1+L26)) -> 5500 | V26: =T26*F26 -> 27.5 | W26: =U26*F26 -> 275 | X26: One page/query assumed; full coverage and pagination unverified. Shared union of followed keys for entity tools; one shared list for global tools. | Y26: Catalogue price/source
A27: T26 | B27: finviz | C27: /get_screener_results | D27: global | E27: global_market | F27: 0.01 | G27: 0 | H27: 0 | I27: 0 | J27: 1 | K27: 1 | L27: 0 | M27: =Profiles!D3 -> 1716 | N27: =IF(H27>0,H27,IF(D27="entity",MAX(Assumptions!$B$7,ROUNDUP(Assumptions!$B$2*Assumptions!$B$7*Assumptions!$B$8,0)),1)) -> 1 | O27: =IF(I27>0,I27,IF(D27="entity",MAX(Assumptions!$B$7,ROUNDUP(Assumptions!$B$3*Assumptions!$B$7*Assumptions!$B$8,0)),1)) -> 1 | P27: =ROUNDUP(Assumptions!$B$2*Assumptions!$B$4*Assumptions!$B$5/J27,0)*K27*(1+L27) -> 1100 | Q27: =ROUNDUP(Assumptions!$B$3*Assumptions!$B$4*Assumptions!$B$5/J27,0)*K27*(1+L27) -> 11000 | R27: =P27*F27 -> 11 | S27: =Q27*F27 -> 110 | T27: =IF(D27="demand",P27*Assumptions!$B$17,ROUNDUP(N27/J27,0)*M27*K27*(1+L27)) -> 1716 | U27: =IF(D27="demand",Q27*Assumptions!$B$17,ROUNDUP(O27/J27,0)*M27*K27*(1+L27)) -> 1716 | V27: =T27*F27 -> 17.16 | W27: =U27*F27 -> 17.16 | X27: One page/query assumed; full coverage and pagination unverified. Shared union of followed keys for entity tools; one shared list for global tools. | Y27: Catalogue price/source
A28: T27 | B28: finviz | C28: /get_insider_trading | D28: global | E28: global_insider | F28: 0.01 | G28: 0 | H28: 0 | I28: 0 | J28: 1 | K28: 1 | L28: 0 | M28: =Profiles!D6 -> 1408 | N28: =IF(H28>0,H28,IF(D28="entity",MAX(Assumptions!$B$7,ROUNDUP(Assumptions!$B$2*Assumptions!$B$7*Assumptions!$B$8,0)),1)) -> 1 | O28: =IF(I28>0,I28,IF(D28="entity",MAX(Assumptions!$B$7,ROUNDUP(Assumptions!$B$3*Assumptions!$B$7*Assumptions!$B$8,0)),1)) -> 1 | P28: =ROUNDUP(Assumptions!$B$2*Assumptions!$B$4*Assumptions!$B$5/J28,0)*K28*(1+L28) -> 1100 | Q28: =ROUNDUP(Assumptions!$B$3*Assumptions!$B$4*Assumptions!$B$5/J28,0)*K28*(1+L28) -> 11000 | R28: =P28*F28 -> 11 | S28: =Q28*F28 -> 110 | T28: =IF(D28="demand",P28*Assumptions!$B$17,ROUNDUP(N28/J28,0)*M28*K28*(1+L28)) -> 1408 | U28: =IF(D28="demand",Q28*Assumptions!$B$17,ROUNDUP(O28/J28,0)*M28*K28*(1+L28)) -> 1408 | V28: =T28*F28 -> 14.08 | W28: =U28*F28 -> 14.08 | X28: One page/query assumed; full coverage and pagination unverified. Shared union of followed keys for entity tools; one shared list for global tools. | Y28: Catalogue price/source
A29: T28 | B29: finviz | C29: /get_ticker_sectors_with_performance | D29: entity | E29: entity_market | F29: 0.01 | G29: 0 | H29: 0 | I29: 0 | J29: 1 | K29: 1 | L29: 0 | M29: =Profiles!D2 -> 1716 | N29: =IF(H29>0,H29,IF(D29="entity",MAX(Assumptions!$B$7,ROUNDUP(Assumptions!$B$2*Assumptions!$B$7*Assumptions!$B$8,0)),1)) -> 100 | O29: =IF(I29>0,I29,IF(D29="entity",MAX(Assumptions!$B$7,ROUNDUP(Assumptions!$B$3*Assumptions!$B$7*Assumptions!$B$8,0)),1)) -> 1000 | P29: =ROUNDUP(Assumptions!$B$2*Assumptions!$B$4*Assumptions!$B$5/J29,0)*K29*(1+L29) -> 1100 | Q29: =ROUNDUP(Assumptions!$B$3*Assumptions!$B$4*Assumptions!$B$5/J29,0)*K29*(1+L29) -> 11000 | R29: =P29*F29 -> 11 | S29: =Q29*F29 -> 110 | T29: =IF(D29="demand",P29*Assumptions!$B$17,ROUNDUP(N29/J29,0)*M29*K29*(1+L29)) -> 171600 | U29: =IF(D29="demand",Q29*Assumptions!$B$17,ROUNDUP(O29/J29,0)*M29*K29*(1+L29)) -> 1716000 | V29: =T29*F29 -> 1716 | W29: =U29*F29 -> 17160 | X29: One page/query assumed; full coverage and pagination unverified. Shared union of followed keys for entity tools; one shared list for global tools. | Y29: Catalogue price/source
A30: T29 | B30: finviz | C30: /get_stock_news_sentiment | D30: entity | E30: entity_news | F30: 0.01 | G30: 0 | H30: 0 | I30: 0 | J30: 1 | K30: 1 | L30: 0 | M30: =Profiles!D4 -> 480 | N30: =IF(H30>0,H30,IF(D30="entity",MAX(Assumptions!$B$7,ROUNDUP(Assumptions!$B$2*Assumptions!$B$7*Assumptions!$B$8,0)),1)) -> 100 | O30: =IF(I30>0,I30,IF(D30="entity",MAX(Assumptions!$B$7,ROUNDUP(Assumptions!$B$3*Assumptions!$B$7*Assumptions!$B$8,0)),1)) -> 1000 | P30: =ROUNDUP(Assumptions!$B$2*Assumptions!$B$4*Assumptions!$B$5/J30,0)*K30*(1+L30) -> 1100 | Q30: =ROUNDUP(Assumptions!$B$3*Assumptions!$B$4*Assumptions!$B$5/J30,0)*K30*(1+L30) -> 11000 | R30: =P30*F30 -> 11 | S30: =Q30*F30 -> 110 | T30: =IF(D30="demand",P30*Assumptions!$B$17,ROUNDUP(N30/J30,0)*M30*K30*(1+L30)) -> 48000 | U30: =IF(D30="demand",Q30*Assumptions!$B$17,ROUNDUP(O30/J30,0)*M30*K30*(1+L30)) -> 480000 | V30: =T30*F30 -> 480 | W30: =U30*F30 -> 4800 | X30: One page/query assumed; full coverage and pagination unverified. Shared union of followed keys for entity tools; one shared list for global tools. | Y30: Catalogue price/source
A31: T30 | B31: finviz | C31: /get_market_movers | D31: global | E31: global_market | F31: 0.01 | G31: 0 | H31: 0 | I31: 0 | J31: 1 | K31: 1 | L31: 0 | M31: =Profiles!D3 -> 1716 | N31: =IF(H31>0,H31,IF(D31="entity",MAX(Assumptions!$B$7,ROUNDUP(Assumptions!$B$2*Assumptions!$B$7*Assumptions!$B$8,0)),1)) -> 1 | O31: =IF(I31>0,I31,IF(D31="entity",MAX(Assumptions!$B$7,ROUNDUP(Assumptions!$B$3*Assumptions!$B$7*Assumptions!$B$8,0)),1)) -> 1 | P31: =ROUNDUP(Assumptions!$B$2*Assumptions!$B$4*Assumptions!$B$5/J31,0)*K31*(1+L31) -> 1100 | Q31: =ROUNDUP(Assumptions!$B$3*Assumptions!$B$4*Assumptions!$B$5/J31,0)*K31*(1+L31) -> 11000 | R31: =P31*F31 -> 11 | S31: =Q31*F31 -> 110 | T31: =IF(D31="demand",P31*Assumptions!$B$17,ROUNDUP(N31/J31,0)*M31*K31*(1+L31)) -> 1716 | U31: =IF(D31="demand",Q31*Assumptions!$B$17,ROUNDUP(O31/J31,0)*M31*K31*(1+L31)) -> 1716 | V31: =T31*F31 -> 17.16 | W31: =U31*F31 -> 17.16 | X31: One page/query assumed; full coverage and pagination unverified. Shared union of followed keys for entity tools; one shared list for global tools. | Y31: Catalogue price/source
A32: T31 | B32: marketbeat | C32: /get_financial_statements | D32: entity | E32: entity_daily | F32: 0.02 | G32: 0 | H32: 0 | I32: 0 | J32: 1 | K32: 1 | L32: 0 | M32: =Profiles!D7 -> 30 | N32: =IF(H32>0,H32,IF(D32="entity",MAX(Assumptions!$B$7,ROUNDUP(Assumptions!$B$2*Assumptions!$B$7*Assumptions!$B$8,0)),1)) -> 100 | O32: =IF(I32>0,I32,IF(D32="entity",MAX(Assumptions!$B$7,ROUNDUP(Assumptions!$B$3*Assumptions!$B$7*Assumptions!$B$8,0)),1)) -> 1000 | P32: =ROUNDUP(Assumptions!$B$2*Assumptions!$B$4*Assumptions!$B$5/J32,0)*K32*(1+L32) -> 1100 | Q32: =ROUNDUP(Assumptions!$B$3*Assumptions!$B$4*Assumptions!$B$5/J32,0)*K32*(1+L32) -> 11000 | R32: =P32*F32 -> 22 | S32: =Q32*F32 -> 220 | T32: =IF(D32="demand",P32*Assumptions!$B$17,ROUNDUP(N32/J32,0)*M32*K32*(1+L32)) -> 3000 | U32: =IF(D32="demand",Q32*Assumptions!$B$17,ROUNDUP(O32/J32,0)*M32*K32*(1+L32)) -> 30000 | V32: =T32*F32 -> 60 | W32: =U32*F32 -> 600 | X32: One page/query assumed; full coverage and pagination unverified. Shared union of followed keys for entity tools; one shared list for global tools. | Y32: Catalogue price/source
A33: T32 | B33: marketbeat | C33: /get_institutional_ownership | D33: entity | E33: entity_daily | F33: 0.01 | G33: 0 | H33: 0 | I33: 0 | J33: 1 | K33: 1 | L33: 0 | M33: =Profiles!D7 -> 30 | N33: =IF(H33>0,H33,IF(D33="entity",MAX(Assumptions!$B$7,ROUNDUP(Assumptions!$B$2*Assumptions!$B$7*Assumptions!$B$8,0)),1)) -> 100 | O33: =IF(I33>0,I33,IF(D33="entity",MAX(Assumptions!$B$7,ROUNDUP(Assumptions!$B$3*Assumptions!$B$7*Assumptions!$B$8,0)),1)) -> 1000 | P33: =ROUNDUP(Assumptions!$B$2*Assumptions!$B$4*Assumptions!$B$5/J33,0)*K33*(1+L33) -> 1100 | Q33: =ROUNDUP(Assumptions!$B$3*Assumptions!$B$4*Assumptions!$B$5/J33,0)*K33*(1+L33) -> 11000 | R33: =P33*F33 -> 11 | S33: =Q33*F33 -> 110 | T33: =IF(D33="demand",P33*Assumptions!$B$17,ROUNDUP(N33/J33,0)*M33*K33*(1+L33)) -> 3000 | U33: =IF(D33="demand",Q33*Assumptions!$B$17,ROUNDUP(O33/J33,0)*M33*K33*(1+L33)) -> 30000 | V33: =T33*F33 -> 30 | W33: =U33*F33 -> 300 | X33: One page/query assumed; full coverage and pagination unverified. Shared union of followed keys for entity tools; one shared list for global tools. | Y33: Catalogue price/source
A34: T33 | B34: marketbeat | C34: /get_analyst_ratings | D34: entity | E34: entity_daily | F34: 0.02 | G34: 0 | H34: 0 | I34: 0 | J34: 1 | K34: 1 | L34: 0 | M34: =Profiles!D7 -> 30 | N34: =IF(H34>0,H34,IF(D34="entity",MAX(Assumptions!$B$7,ROUNDUP(Assumptions!$B$2*Assumptions!$B$7*Assumptions!$B$8,0)),1)) -> 100 | O34: =IF(I34>0,I34,IF(D34="entity",MAX(Assumptions!$B$7,ROUNDUP(Assumptions!$B$3*Assumptions!$B$7*Assumptions!$B$8,0)),1)) -> 1000 | P34: =ROUNDUP(Assumptions!$B$2*Assumptions!$B$4*Assumptions!$B$5/J34,0)*K34*(1+L34) -> 1100 | Q34: =ROUNDUP(Assumptions!$B$3*Assumptions!$B$4*Assumptions!$B$5/J34,0)*K34*(1+L34) -> 11000 | R34: =P34*F34 -> 22 | S34: =Q34*F34 -> 220 | T34: =IF(D34="demand",P34*Assumptions!$B$17,ROUNDUP(N34/J34,0)*M34*K34*(1+L34)) -> 3000 | U34: =IF(D34="demand",Q34*Assumptions!$B$17,ROUNDUP(O34/J34,0)*M34*K34*(1+L34)) -> 30000 | V34: =T34*F34 -> 60 | W34: =U34*F34 -> 600 | X34: One page/query assumed; full coverage and pagination unverified. Shared union of followed keys for entity tools; one shared list for global tools. | Y34: Catalogue price/source
A35: T34 | B35: marketbeat | C35: /get_insider_trades | D35: entity | E35: entity_hourly | F35: 0.01 | G35: 0 | H35: 0 | I35: 0 | J35: 1 | K35: 1 | L35: 0 | M35: =Profiles!D5 -> 352 | N35: =IF(H35>0,H35,IF(D35="entity",MAX(Assumptions!$B$7,ROUNDUP(Assumptions!$B$2*Assumptions!$B$7*Assumptions!$B$8,0)),1)) -> 100 | O35: =IF(I35>0,I35,IF(D35="entity",MAX(Assumptions!$B$7,ROUNDUP(Assumptions!$B$3*Assumptions!$B$7*Assumptions!$B$8,0)),1)) -> 1000 | P35: =ROUNDUP(Assumptions!$B$2*Assumptions!$B$4*Assumptions!$B$5/J35,0)*K35*(1+L35) -> 1100 | Q35: =ROUNDUP(Assumptions!$B$3*Assumptions!$B$4*Assumptions!$B$5/J35,0)*K35*(1+L35) -> 11000 | R35: =P35*F35 -> 11 | S35: =Q35*F35 -> 110 | T35: =IF(D35="demand",P35*Assumptions!$B$17,ROUNDUP(N35/J35,0)*M35*K35*(1+L35)) -> 35200 | U35: =IF(D35="demand",Q35*Assumptions!$B$17,ROUNDUP(O35/J35,0)*M35*K35*(1+L35)) -> 352000 | V35: =T35*F35 -> 352 | W35: =U35*F35 -> 3520 | X35: One page/query assumed; full coverage and pagination unverified. Shared union of followed keys for entity tools; one shared list for global tools. | Y35: Catalogue price/source
A36: T35 | B36: marketbeat | C36: /search_stocks | D36: demand | E36: lookup_demand | F36: 0.01 | G36: 0 | H36: 0 | I36: 0 | J36: 1 | K36: 1 | L36: 0 | M36: =Profiles!D9 -> 0 | N36: =IF(H36>0,H36,IF(D36="entity",MAX(Assumptions!$B$7,ROUNDUP(Assumptions!$B$2*Assumptions!$B$7*Assumptions!$B$8,0)),1)) -> 1 | O36: =IF(I36>0,I36,IF(D36="entity",MAX(Assumptions!$B$7,ROUNDUP(Assumptions!$B$3*Assumptions!$B$7*Assumptions!$B$8,0)),1)) -> 1 | P36: =ROUNDUP(Assumptions!$B$2*Assumptions!$B$4*Assumptions!$B$5/J36,0)*K36*(1+L36) -> 1100 | Q36: =ROUNDUP(Assumptions!$B$3*Assumptions!$B$4*Assumptions!$B$5/J36,0)*K36*(1+L36) -> 11000 | R36: =P36*F36 -> 11 | S36: =Q36*F36 -> 110 | T36: =IF(D36="demand",P36*Assumptions!$B$17,ROUNDUP(N36/J36,0)*M36*K36*(1+L36)) -> 550 | U36: =IF(D36="demand",Q36*Assumptions!$B$17,ROUNDUP(O36/J36,0)*M36*K36*(1+L36)) -> 5500 | V36: =T36*F36 -> 5.5 | W36: =U36*F36 -> 55 | X36: One page/query assumed; full coverage and pagination unverified. Shared union of followed keys for entity tools; one shared list for global tools. | Y36: Catalogue price/source
A37: T36 | B37: marketbeat | C37: /get_options_chain | D37: entity | E37: entity_market | F37: 0.01 | G37: 0 | H37: 0 | I37: 0 | J37: 1 | K37: 1 | L37: 0 | M37: =Profiles!D2 -> 1716 | N37: =IF(H37>0,H37,IF(D37="entity",MAX(Assumptions!$B$7,ROUNDUP(Assumptions!$B$2*Assumptions!$B$7*Assumptions!$B$8,0)),1)) -> 100 | O37: =IF(I37>0,I37,IF(D37="entity",MAX(Assumptions!$B$7,ROUNDUP(Assumptions!$B$3*Assumptions!$B$7*Assumptions!$B$8,0)),1)) -> 1000 | P37: =ROUNDUP(Assumptions!$B$2*Assumptions!$B$4*Assumptions!$B$5/J37,0)*K37*(1+L37) -> 1100 | Q37: =ROUNDUP(Assumptions!$B$3*Assumptions!$B$4*Assumptions!$B$5/J37,0)*K37*(1+L37) -> 11000 | R37: =P37*F37 -> 11 | S37: =Q37*F37 -> 110 | T37: =IF(D37="demand",P37*Assumptions!$B$17,ROUNDUP(N37/J37,0)*M37*K37*(1+L37)) -> 171600 | U37: =IF(D37="demand",Q37*Assumptions!$B$17,ROUNDUP(O37/J37,0)*M37*K37*(1+L37)) -> 1716000 | V37: =T37*F37 -> 1716 | W37: =U37*F37 -> 17160 | X37: One page/query assumed; full coverage and pagination unverified. Shared union of followed keys for entity tools; one shared list for global tools. | Y37: Catalogue price/source
A38: T37 | B38: marketbeat | C38: /get_stock_overview | D38: entity | E38: entity_daily | F38: 0.01 | G38: 0 | H38: 0 | I38: 0 | J38: 1 | K38: 1 | L38: 0 | M38: =Profiles!D7 -> 30 | N38: =IF(H38>0,H38,IF(D38="entity",MAX(Assumptions!$B$7,ROUNDUP(Assumptions!$B$2*Assumptions!$B$7*Assumptions!$B$8,0)),1)) -> 100 | O38: =IF(I38>0,I38,IF(D38="entity",MAX(Assumptions!$B$7,ROUNDUP(Assumptions!$B$3*Assumptions!$B$7*Assumptions!$B$8,0)),1)) -> 1000 | P38: =ROUNDUP(Assumptions!$B$2*Assumptions!$B$4*Assumptions!$B$5/J38,0)*K38*(1+L38) -> 1100 | Q38: =ROUNDUP(Assumptions!$B$3*Assumptions!$B$4*Assumptions!$B$5/J38,0)*K38*(1+L38) -> 11000 | R38: =P38*F38 -> 11 | S38: =Q38*F38 -> 110 | T38: =IF(D38="demand",P38*Assumptions!$B$17,ROUNDUP(N38/J38,0)*M38*K38*(1+L38)) -> 3000 | U38: =IF(D38="demand",Q38*Assumptions!$B$17,ROUNDUP(O38/J38,0)*M38*K38*(1+L38)) -> 30000 | V38: =T38*F38 -> 30 | W38: =U38*F38 -> 300 | X38: One page/query assumed; full coverage and pagination unverified. Shared union of followed keys for entity tools; one shared list for global tools. | Y38: Catalogue price/source
A39: T38 | B39: marketbeat | C39: /get_earnings | D39: entity | E39: entity_daily | F39: 0.01 | G39: 0 | H39: 0 | I39: 0 | J39: 1 | K39: 1 | L39: 0 | M39: =Profiles!D7 -> 30 | N39: =IF(H39>0,H39,IF(D39="entity",MAX(Assumptions!$B$7,ROUNDUP(Assumptions!$B$2*Assumptions!$B$7*Assumptions!$B$8,0)),1)) -> 100 | O39: =IF(I39>0,I39,IF(D39="entity",MAX(Assumptions!$B$7,ROUNDUP(Assumptions!$B$3*Assumptions!$B$7*Assumptions!$B$8,0)),1)) -> 1000 | P39: =ROUNDUP(Assumptions!$B$2*Assumptions!$B$4*Assumptions!$B$5/J39,0)*K39*(1+L39) -> 1100 | Q39: =ROUNDUP(Assumptions!$B$3*Assumptions!$B$4*Assumptions!$B$5/J39,0)*K39*(1+L39) -> 11000 | R39: =P39*F39 -> 11 | S39: =Q39*F39 -> 110 | T39: =IF(D39="demand",P39*Assumptions!$B$17,ROUNDUP(N39/J39,0)*M39*K39*(1+L39)) -> 3000 | U39: =IF(D39="demand",Q39*Assumptions!$B$17,ROUNDUP(O39/J39,0)*M39*K39*(1+L39)) -> 30000 | V39: =T39*F39 -> 30 | W39: =U39*F39 -> 300 | X39: One page/query assumed; full coverage and pagination unverified. Shared union of followed keys for entity tools; one shared list for global tools. | Y39: Catalogue price/source
A40: T39 | B40: marketbeat | C40: /get_competitors | D40: entity | E40: entity_daily | F40: 0.01 | G40: 0 | H40: 0 | I40: 0 | J40: 1 | K40: 1 | L40: 0 | M40: =Profiles!D7 -> 30 | N40: =IF(H40>0,H40,IF(D40="entity",MAX(Assumptions!$B$7,ROUNDUP(Assumptions!$B$2*Assumptions!$B$7*Assumptions!$B$8,0)),1)) -> 100 | O40: =IF(I40>0,I40,IF(D40="entity",MAX(Assumptions!$B$7,ROUNDUP(Assumptions!$B$3*Assumptions!$B$7*Assumptions!$B$8,0)),1)) -> 1000 | P40: =ROUNDUP(Assumptions!$B$2*Assumptions!$B$4*Assumptions!$B$5/J40,0)*K40*(1+L40) -> 1100 | Q40: =ROUNDUP(Assumptions!$B$3*Assumptions!$B$4*Assumptions!$B$5/J40,0)*K40*(1+L40) -> 11000 | R40: =P40*F40 -> 11 | S40: =Q40*F40 -> 110 | T40: =IF(D40="demand",P40*Assumptions!$B$17,ROUNDUP(N40/J40,0)*M40*K40*(1+L40)) -> 3000 | U40: =IF(D40="demand",Q40*Assumptions!$B$17,ROUNDUP(O40/J40,0)*M40*K40*(1+L40)) -> 30000 | V40: =T40*F40 -> 30 | W40: =U40*F40 -> 300 | X40: One page/query assumed; full coverage and pagination unverified. Shared union of followed keys for entity tools; one shared list for global tools. | Y40: Catalogue price/source
A41: T40 | B41: marketbeat | C41: /get_marketrank | D41: entity | E41: entity_daily | F41: 0.01 | G41: 0 | H41: 0 | I41: 0 | J41: 1 | K41: 1 | L41: 0 | M41: =Profiles!D7 -> 30 | N41: =IF(H41>0,H41,IF(D41="entity",MAX(Assumptions!$B$7,ROUNDUP(Assumptions!$B$2*Assumptions!$B$7*Assumptions!$B$8,0)),1)) -> 100 | O41: =IF(I41>0,I41,IF(D41="entity",MAX(Assumptions!$B$7,ROUNDUP(Assumptions!$B$3*Assumptions!$B$7*Assumptions!$B$8,0)),1)) -> 1000 | P41: =ROUNDUP(Assumptions!$B$2*Assumptions!$B$4*Assumptions!$B$5/J41,0)*K41*(1+L41) -> 1100 | Q41: =ROUNDUP(Assumptions!$B$3*Assumptions!$B$4*Assumptions!$B$5/J41,0)*K41*(1+L41) -> 11000 | R41: =P41*F41 -> 11 | S41: =Q41*F41 -> 110 | T41: =IF(D41="demand",P41*Assumptions!$B$17,ROUNDUP(N41/J41,0)*M41*K41*(1+L41)) -> 3000 | U41: =IF(D41="demand",Q41*Assumptions!$B$17,ROUNDUP(O41/J41,0)*M41*K41*(1+L41)) -> 30000 | V41: =T41*F41 -> 30 | W41: =U41*F41 -> 300 | X41: One page/query assumed; full coverage and pagination unverified. Shared union of followed keys for entity tools; one shared list for global tools. | Y41: Catalogue price/source
A42: T41 | B42: marketbeat | C42: /get_stock_headlines | D42: entity | E42: entity_news | F42: 0.01 | G42: 0 | H42: 0 | I42: 0 | J42: 1 | K42: 1 | L42: 0 | M42: =Profiles!D4 -> 480 | N42: =IF(H42>0,H42,IF(D42="entity",MAX(Assumptions!$B$7,ROUNDUP(Assumptions!$B$2*Assumptions!$B$7*Assumptions!$B$8,0)),1)) -> 100 | O42: =IF(I42>0,I42,IF(D42="entity",MAX(Assumptions!$B$7,ROUNDUP(Assumptions!$B$3*Assumptions!$B$7*Assumptions!$B$8,0)),1)) -> 1000 | P42: =ROUNDUP(Assumptions!$B$2*Assumptions!$B$4*Assumptions!$B$5/J42,0)*K42*(1+L42) -> 1100 | Q42: =ROUNDUP(Assumptions!$B$3*Assumptions!$B$4*Assumptions!$B$5/J42,0)*K42*(1+L42) -> 11000 | R42: =P42*F42 -> 11 | S42: =Q42*F42 -> 110 | T42: =IF(D42="demand",P42*Assumptions!$B$17,ROUNDUP(N42/J42,0)*M42*K42*(1+L42)) -> 48000 | U42: =IF(D42="demand",Q42*Assumptions!$B$17,ROUNDUP(O42/J42,0)*M42*K42*(1+L42)) -> 480000 | V42: =T42*F42 -> 480 | W42: =U42*F42 -> 4800 | X42: One page/query assumed; full coverage and pagination unverified. Shared union of followed keys for entity tools; one shared list for global tools. | Y42: Catalogue price/source
A43: T42 | B43: marketbeat | C43: /get_short_interest | D43: entity | E43: entity_daily | F43: 0.01 | G43: 0 | H43: 0 | I43: 0 | J43: 1 | K43: 1 | L43: 0 | M43: =Profiles!D7 -> 30 | N43: =IF(H43>0,H43,IF(D43="entity",MAX(Assumptions!$B$7,ROUNDUP(Assumptions!$B$2*Assumptions!$B$7*Assumptions!$B$8,0)),1)) -> 100 | O43: =IF(I43>0,I43,IF(D43="entity",MAX(Assumptions!$B$7,ROUNDUP(Assumptions!$B$3*Assumptions!$B$7*Assumptions!$B$8,0)),1)) -> 1000 | P43: =ROUNDUP(Assumptions!$B$2*Assumptions!$B$4*Assumptions!$B$5/J43,0)*K43*(1+L43) -> 1100 | Q43: =ROUNDUP(Assumptions!$B$3*Assumptions!$B$4*Assumptions!$B$5/J43,0)*K43*(1+L43) -> 11000 | R43: =P43*F43 -> 11 | S43: =Q43*F43 -> 110 | T43: =IF(D43="demand",P43*Assumptions!$B$17,ROUNDUP(N43/J43,0)*M43*K43*(1+L43)) -> 3000 | U43: =IF(D43="demand",Q43*Assumptions!$B$17,ROUNDUP(O43/J43,0)*M43*K43*(1+L43)) -> 30000 | V43: =T43*F43 -> 30 | W43: =U43*F43 -> 300 | X43: One page/query assumed; full coverage and pagination unverified. Shared union of followed keys for entity tools; one shared list for global tools. | Y43: Catalogue price/source
A44: T43 | B44: marketbeat | C44: /get_profitability_metrics | D44: entity | E44: entity_daily | F44: 0.01 | G44: 0 | H44: 0 | I44: 0 | J44: 1 | K44: 1 | L44: 0 | M44: =Profiles!D7 -> 30 | N44: =IF(H44>0,H44,IF(D44="entity",MAX(Assumptions!$B$7,ROUNDUP(Assumptions!$B$2*Assumptions!$B$7*Assumptions!$B$8,0)),1)) -> 100 | O44: =IF(I44>0,I44,IF(D44="entity",MAX(Assumptions!$B$7,ROUNDUP(Assumptions!$B$3*Assumptions!$B$7*Assumptions!$B$8,0)),1)) -> 1000 | P44: =ROUNDUP(Assumptions!$B$2*Assumptions!$B$4*Assumptions!$B$5/J44,0)*K44*(1+L44) -> 1100 | Q44: =ROUNDUP(Assumptions!$B$3*Assumptions!$B$4*Assumptions!$B$5/J44,0)*K44*(1+L44) -> 11000 | R44: =P44*F44 -> 11 | S44: =Q44*F44 -> 110 | T44: =IF(D44="demand",P44*Assumptions!$B$17,ROUNDUP(N44/J44,0)*M44*K44*(1+L44)) -> 3000 | U44: =IF(D44="demand",Q44*Assumptions!$B$17,ROUNDUP(O44/J44,0)*M44*K44*(1+L44)) -> 30000 | V44: =T44*F44 -> 30 | W44: =U44*F44 -> 300 | X44: One page/query assumed; full coverage and pagination unverified. Shared union of followed keys for entity tools; one shared list for global tools. | Y44: Catalogue price/source
A45: T44 | B45: marketbeat | C45: /get_stock_forecast | D45: entity | E45: entity_daily | F45: 0.01 | G45: 0 | H45: 0 | I45: 0 | J45: 1 | K45: 1 | L45: 0 | M45: =Profiles!D7 -> 30 | N45: =IF(H45>0,H45,IF(D45="entity",MAX(Assumptions!$B$7,ROUNDUP(Assumptions!$B$2*Assumptions!$B$7*Assumptions!$B$8,0)),1)) -> 100 | O45: =IF(I45>0,I45,IF(D45="entity",MAX(Assumptions!$B$7,ROUNDUP(Assumptions!$B$3*Assumptions!$B$7*Assumptions!$B$8,0)),1)) -> 1000 | P45: =ROUNDUP(Assumptions!$B$2*Assumptions!$B$4*Assumptions!$B$5/J45,0)*K45*(1+L45) -> 1100 | Q45: =ROUNDUP(Assumptions!$B$3*Assumptions!$B$4*Assumptions!$B$5/J45,0)*K45*(1+L45) -> 11000 | R45: =P45*F45 -> 11 | S45: =Q45*F45 -> 110 | T45: =IF(D45="demand",P45*Assumptions!$B$17,ROUNDUP(N45/J45,0)*M45*K45*(1+L45)) -> 3000 | U45: =IF(D45="demand",Q45*Assumptions!$B$17,ROUNDUP(O45/J45,0)*M45*K45*(1+L45)) -> 30000 | V45: =T45*F45 -> 30 | W45: =U45*F45 -> 300 | X45: One page/query assumed; full coverage and pagination unverified. Shared union of followed keys for entity tools; one shared list for global tools. | Y45: Catalogue price/source
A46: T45 | B46: stockanalysis | C46: /get_stock_list | D46: global | E46: global_daily | F46: 0.01 | G46: 0 | H46: 0 | I46: 0 | J46: 1 | K46: 1 | L46: 0 | M46: =Profiles!D8 -> 30 | N46: =IF(H46>0,H46,IF(D46="entity",MAX(Assumptions!$B$7,ROUNDUP(Assumptions!$B$2*Assumptions!$B$7*Assumptions!$B$8,0)),1)) -> 1 | O46: =IF(I46>0,I46,IF(D46="entity",MAX(Assumptions!$B$7,ROUNDUP(Assumptions!$B$3*Assumptions!$B$7*Assumptions!$B$8,0)),1)) -> 1 | P46: =ROUNDUP(Assumptions!$B$2*Assumptions!$B$4*Assumptions!$B$5/J46,0)*K46*(1+L46) -> 1100 | Q46: =ROUNDUP(Assumptions!$B$3*Assumptions!$B$4*Assumptions!$B$5/J46,0)*K46*(1+L46) -> 11000 | R46: =P46*F46 -> 11 | S46: =Q46*F46 -> 110 | T46: =IF(D46="demand",P46*Assumptions!$B$17,ROUNDUP(N46/J46,0)*M46*K46*(1+L46)) -> 30 | U46: =IF(D46="demand",Q46*Assumptions!$B$17,ROUNDUP(O46/J46,0)*M46*K46*(1+L46)) -> 30 | V46: =T46*F46 -> 0.3 | W46: =U46*F46 -> 0.3 | X46: One page/query assumed; full coverage and pagination unverified. Shared union of followed keys for entity tools; one shared list for global tools. | Y46: Catalogue price/source
A47: T46 | B47: stockanalysis | C47: /search_stocks | D47: demand | E47: lookup_demand | F47: 0.01 | G47: 0 | H47: 0 | I47: 0 | J47: 1 | K47: 1 | L47: 0 | M47: =Profiles!D9 -> 0 | N47: =IF(H47>0,H47,IF(D47="entity",MAX(Assumptions!$B$7,ROUNDUP(Assumptions!$B$2*Assumptions!$B$7*Assumptions!$B$8,0)),1)) -> 1 | O47: =IF(I47>0,I47,IF(D47="entity",MAX(Assumptions!$B$7,ROUNDUP(Assumptions!$B$3*Assumptions!$B$7*Assumptions!$B$8,0)),1)) -> 1 | P47: =ROUNDUP(Assumptions!$B$2*Assumptions!$B$4*Assumptions!$B$5/J47,0)*K47*(1+L47) -> 1100 | Q47: =ROUNDUP(Assumptions!$B$3*Assumptions!$B$4*Assumptions!$B$5/J47,0)*K47*(1+L47) -> 11000 | R47: =P47*F47 -> 11 | S47: =Q47*F47 -> 110 | T47: =IF(D47="demand",P47*Assumptions!$B$17,ROUNDUP(N47/J47,0)*M47*K47*(1+L47)) -> 550 | U47: =IF(D47="demand",Q47*Assumptions!$B$17,ROUNDUP(O47/J47,0)*M47*K47*(1+L47)) -> 5500 | V47: =T47*F47 -> 5.5 | W47: =U47*F47 -> 55 | X47: One page/query assumed; full coverage and pagination unverified. Shared union of followed keys for entity tools; one shared list for global tools. | Y47: Catalogue price/source
A48: T47 | B48: stockanalysis | C48: /get_stock_financials_income | D48: entity | E48: entity_daily | F48: 0.01 | G48: 0 | H48: 0 | I48: 0 | J48: 1 | K48: 1 | L48: 0 | M48: =Profiles!D7 -> 30 | N48: =IF(H48>0,H48,IF(D48="entity",MAX(Assumptions!$B$7,ROUNDUP(Assumptions!$B$2*Assumptions!$B$7*Assumptions!$B$8,0)),1)) -> 100 | O48: =IF(I48>0,I48,IF(D48="entity",MAX(Assumptions!$B$7,ROUNDUP(Assumptions!$B$3*Assumptions!$B$7*Assumptions!$B$8,0)),1)) -> 1000 | P48: =ROUNDUP(Assumptions!$B$2*Assumptions!$B$4*Assumptions!$B$5/J48,0)*K48*(1+L48) -> 1100 | Q48: =ROUNDUP(Assumptions!$B$3*Assumptions!$B$4*Assumptions!$B$5/J48,0)*K48*(1+L48) -> 11000 | R48: =P48*F48 -> 11 | S48: =Q48*F48 -> 110 | T48: =IF(D48="demand",P48*Assumptions!$B$17,ROUNDUP(N48/J48,0)*M48*K48*(1+L48)) -> 3000 | U48: =IF(D48="demand",Q48*Assumptions!$B$17,ROUNDUP(O48/J48,0)*M48*K48*(1+L48)) -> 30000 | V48: =T48*F48 -> 30 | W48: =U48*F48 -> 300 | X48: One page/query assumed; full coverage and pagination unverified. Shared union of followed keys for entity tools; one shared list for global tools. | Y48: Catalogue price/source
A49: T48 | B49: stockanalysis | C49: /get_market_movers_premarket | D49: global | E49: global_premarket | F49: 0.01 | G49: 0 | H49: 0 | I49: 0 | J49: 1 | K49: 1 | L49: 0 | M49: =Profiles!D12 -> 1452 | N49: =IF(H49>0,H49,IF(D49="entity",MAX(Assumptions!$B$7,ROUNDUP(Assumptions!$B$2*Assumptions!$B$7*Assumptions!$B$8,0)),1)) -> 1 | O49: =IF(I49>0,I49,IF(D49="entity",MAX(Assumptions!$B$7,ROUNDUP(Assumptions!$B$3*Assumptions!$B$7*Assumptions!$B$8,0)),1)) -> 1 | P49: =ROUNDUP(Assumptions!$B$2*Assumptions!$B$4*Assumptions!$B$5/J49,0)*K49*(1+L49) -> 1100 | Q49: =ROUNDUP(Assumptions!$B$3*Assumptions!$B$4*Assumptions!$B$5/J49,0)*K49*(1+L49) -> 11000 | R49: =P49*F49 -> 11 | S49: =Q49*F49 -> 110 | T49: =IF(D49="demand",P49*Assumptions!$B$17,ROUNDUP(N49/J49,0)*M49*K49*(1+L49)) -> 1452 | U49: =IF(D49="demand",Q49*Assumptions!$B$17,ROUNDUP(O49/J49,0)*M49*K49*(1+L49)) -> 1452 | V49: =T49*F49 -> 14.52 | W49: =U49*F49 -> 14.52 | X49: One page/query assumed; full coverage and pagination unverified. Shared union of followed keys for entity tools; one shared list for global tools. | Y49: Catalogue price/source
A50: T49 | B50: stockanalysis | C50: /get_stock_statistics | D50: entity | E50: entity_daily | F50: 0.01 | G50: 0 | H50: 0 | I50: 0 | J50: 1 | K50: 1 | L50: 0 | M50: =Profiles!D7 -> 30 | N50: =IF(H50>0,H50,IF(D50="entity",MAX(Assumptions!$B$7,ROUNDUP(Assumptions!$B$2*Assumptions!$B$7*Assumptions!$B$8,0)),1)) -> 100 | O50: =IF(I50>0,I50,IF(D50="entity",MAX(Assumptions!$B$7,ROUNDUP(Assumptions!$B$3*Assumptions!$B$7*Assumptions!$B$8,0)),1)) -> 1000 | P50: =ROUNDUP(Assumptions!$B$2*Assumptions!$B$4*Assumptions!$B$5/J50,0)*K50*(1+L50) -> 1100 | Q50: =ROUNDUP(Assumptions!$B$3*Assumptions!$B$4*Assumptions!$B$5/J50,0)*K50*(1+L50) -> 11000 | R50: =P50*F50 -> 11 | S50: =Q50*F50 -> 110 | T50: =IF(D50="demand",P50*Assumptions!$B$17,ROUNDUP(N50/J50,0)*M50*K50*(1+L50)) -> 3000 | U50: =IF(D50="demand",Q50*Assumptions!$B$17,ROUNDUP(O50/J50,0)*M50*K50*(1+L50)) -> 30000 | V50: =T50*F50 -> 30 | W50: =U50*F50 -> 300 | X50: One page/query assumed; full coverage and pagination unverified. Shared union of followed keys for entity tools; one shared list for global tools. | Y50: Catalogue price/source
A51: T50 | B51: stockanalysis | C51: /get_ipo_calendar | D51: global | E51: global_daily | F51: 0.01 | G51: 0 | H51: 0 | I51: 0 | J51: 1 | K51: 1 | L51: 0 | M51: =Profiles!D8 -> 30 | N51: =IF(H51>0,H51,IF(D51="entity",MAX(Assumptions!$B$7,ROUNDUP(Assumptions!$B$2*Assumptions!$B$7*Assumptions!$B$8,0)),1)) -> 1 | O51: =IF(I51>0,I51,IF(D51="entity",MAX(Assumptions!$B$7,ROUNDUP(Assumptions!$B$3*Assumptions!$B$7*Assumptions!$B$8,0)),1)) -> 1 | P51: =ROUNDUP(Assumptions!$B$2*Assumptions!$B$4*Assumptions!$B$5/J51,0)*K51*(1+L51) -> 1100 | Q51: =ROUNDUP(Assumptions!$B$3*Assumptions!$B$4*Assumptions!$B$5/J51,0)*K51*(1+L51) -> 11000 | R51: =P51*F51 -> 11 | S51: =Q51*F51 -> 110 | T51: =IF(D51="demand",P51*Assumptions!$B$17,ROUNDUP(N51/J51,0)*M51*K51*(1+L51)) -> 30 | U51: =IF(D51="demand",Q51*Assumptions!$B$17,ROUNDUP(O51/J51,0)*M51*K51*(1+L51)) -> 30 | V51: =T51*F51 -> 0.3 | W51: =U51*F51 -> 0.3 | X51: One page/query assumed; full coverage and pagination unverified. Shared union of followed keys for entity tools; one shared list for global tools. | Y51: Catalogue price/source
A52: T51 | B52: stockanalysis | C52: /get_stock_overview | D52: entity | E52: entity_market | F52: 0.01 | G52: 0 | H52: 0 | I52: 0 | J52: 1 | K52: 1 | L52: 0 | M52: =Profiles!D2 -> 1716 | N52: =IF(H52>0,H52,IF(D52="entity",MAX(Assumptions!$B$7,ROUNDUP(Assumptions!$B$2*Assumptions!$B$7*Assumptions!$B$8,0)),1)) -> 100 | O52: =IF(I52>0,I52,IF(D52="entity",MAX(Assumptions!$B$7,ROUNDUP(Assumptions!$B$3*Assumptions!$B$7*Assumptions!$B$8,0)),1)) -> 1000 | P52: =ROUNDUP(Assumptions!$B$2*Assumptions!$B$4*Assumptions!$B$5/J52,0)*K52*(1+L52) -> 1100 | Q52: =ROUNDUP(Assumptions!$B$3*Assumptions!$B$4*Assumptions!$B$5/J52,0)*K52*(1+L52) -> 11000 | R52: =P52*F52 -> 11 | S52: =Q52*F52 -> 110 | T52: =IF(D52="demand",P52*Assumptions!$B$17,ROUNDUP(N52/J52,0)*M52*K52*(1+L52)) -> 171600 | U52: =IF(D52="demand",Q52*Assumptions!$B$17,ROUNDUP(O52/J52,0)*M52*K52*(1+L52)) -> 1716000 | V52: =T52*F52 -> 1716 | W52: =U52*F52 -> 17160 | X52: One page/query assumed; full coverage and pagination unverified. Shared union of followed keys for entity tools; one shared list for global tools. | Y52: Catalogue price/source
A53: T52 | B53: defillama | C53: /equities/v1/statements | D53: entity | E53: entity_daily | F53: 0.0006 | G53: 0 | H53: 0 | I53: 0 | J53: 1 | K53: 1 | L53: 0 | M53: =Profiles!D7 -> 30 | N53: =IF(H53>0,H53,IF(D53="entity",MAX(Assumptions!$B$7,ROUNDUP(Assumptions!$B$2*Assumptions!$B$7*Assumptions!$B$8,0)),1)) -> 100 | O53: =IF(I53>0,I53,IF(D53="entity",MAX(Assumptions!$B$7,ROUNDUP(Assumptions!$B$3*Assumptions!$B$7*Assumptions!$B$8,0)),1)) -> 1000 | P53: =ROUNDUP(Assumptions!$B$2*Assumptions!$B$4*Assumptions!$B$5/J53,0)*K53*(1+L53) -> 1100 | Q53: =ROUNDUP(Assumptions!$B$3*Assumptions!$B$4*Assumptions!$B$5/J53,0)*K53*(1+L53) -> 11000 | R53: =P53*F53 -> 0.66 | S53: =Q53*F53 -> 6.6 | T53: =IF(D53="demand",P53*Assumptions!$B$17,ROUNDUP(N53/J53,0)*M53*K53*(1+L53)) -> 3000 | U53: =IF(D53="demand",Q53*Assumptions!$B$17,ROUNDUP(O53/J53,0)*M53*K53*(1+L53)) -> 30000 | V53: =T53*F53 -> 1.8 | W53: =U53*F53 -> 18 | X53: One page/query assumed; full coverage and pagination unverified. Shared union of followed keys for entity tools; one shared list for global tools. | Y53: Catalogue price/source
A54: T53 | B54: defillama | C54: /equities/v1/filings | D54: entity | E54: entity_hourly | F54: 0.0006 | G54: 0 | H54: 0 | I54: 0 | J54: 1 | K54: 1 | L54: 0 | M54: =Profiles!D5 -> 352 | N54: =IF(H54>0,H54,IF(D54="entity",MAX(Assumptions!$B$7,ROUNDUP(Assumptions!$B$2*Assumptions!$B$7*Assumptions!$B$8,0)),1)) -> 100 | O54: =IF(I54>0,I54,IF(D54="entity",MAX(Assumptions!$B$7,ROUNDUP(Assumptions!$B$3*Assumptions!$B$7*Assumptions!$B$8,0)),1)) -> 1000 | P54: =ROUNDUP(Assumptions!$B$2*Assumptions!$B$4*Assumptions!$B$5/J54,0)*K54*(1+L54) -> 1100 | Q54: =ROUNDUP(Assumptions!$B$3*Assumptions!$B$4*Assumptions!$B$5/J54,0)*K54*(1+L54) -> 11000 | R54: =P54*F54 -> 0.66 | S54: =Q54*F54 -> 6.6 | T54: =IF(D54="demand",P54*Assumptions!$B$17,ROUNDUP(N54/J54,0)*M54*K54*(1+L54)) -> 35200 | U54: =IF(D54="demand",Q54*Assumptions!$B$17,ROUNDUP(O54/J54,0)*M54*K54*(1+L54)) -> 352000 | V54: =T54*F54 -> 21.12 | W54: =U54*F54 -> 211.2 | X54: One page/query assumed; full coverage and pagination unverified. Shared union of followed keys for entity tools; one shared list for global tools. | Y54: Catalogue price/source
A55: T54 | B55: defillama | C55: /equities/v1/summary | D55: entity | E55: entity_market | F55: 0.0006 | G55: 0 | H55: 0 | I55: 0 | J55: 1 | K55: 1 | L55: 0 | M55: =Profiles!D2 -> 1716 | N55: =IF(H55>0,H55,IF(D55="entity",MAX(Assumptions!$B$7,ROUNDUP(Assumptions!$B$2*Assumptions!$B$7*Assumptions!$B$8,0)),1)) -> 100 | O55: =IF(I55>0,I55,IF(D55="entity",MAX(Assumptions!$B$7,ROUNDUP(Assumptions!$B$3*Assumptions!$B$7*Assumptions!$B$8,0)),1)) -> 1000 | P55: =ROUNDUP(Assumptions!$B$2*Assumptions!$B$4*Assumptions!$B$5/J55,0)*K55*(1+L55) -> 1100 | Q55: =ROUNDUP(Assumptions!$B$3*Assumptions!$B$4*Assumptions!$B$5/J55,0)*K55*(1+L55) -> 11000 | R55: =P55*F55 -> 0.66 | S55: =Q55*F55 -> 6.6 | T55: =IF(D55="demand",P55*Assumptions!$B$17,ROUNDUP(N55/J55,0)*M55*K55*(1+L55)) -> 171600 | U55: =IF(D55="demand",Q55*Assumptions!$B$17,ROUNDUP(O55/J55,0)*M55*K55*(1+L55)) -> 1716000 | V55: =T55*F55 -> 102.96 | W55: =U55*F55 -> 1029.6 | X55: One page/query assumed; full coverage and pagination unverified. Shared union of followed keys for entity tools; one shared list for global tools. | Y55: Catalogue price/source
A56: T55 | B56: defillama | C56: /equities/v1/price-history | D56: entity | E56: entity_daily | F56: 0.0006 | G56: 0 | H56: 0 | I56: 0 | J56: 1 | K56: 1 | L56: 0 | M56: =Profiles!D7 -> 30 | N56: =IF(H56>0,H56,IF(D56="entity",MAX(Assumptions!$B$7,ROUNDUP(Assumptions!$B$2*Assumptions!$B$7*Assumptions!$B$8,0)),1)) -> 100 | O56: =IF(I56>0,I56,IF(D56="entity",MAX(Assumptions!$B$7,ROUNDUP(Assumptions!$B$3*Assumptions!$B$7*Assumptions!$B$8,0)),1)) -> 1000 | P56: =ROUNDUP(Assumptions!$B$2*Assumptions!$B$4*Assumptions!$B$5/J56,0)*K56*(1+L56) -> 1100 | Q56: =ROUNDUP(Assumptions!$B$3*Assumptions!$B$4*Assumptions!$B$5/J56,0)*K56*(1+L56) -> 11000 | R56: =P56*F56 -> 0.66 | S56: =Q56*F56 -> 6.6 | T56: =IF(D56="demand",P56*Assumptions!$B$17,ROUNDUP(N56/J56,0)*M56*K56*(1+L56)) -> 3000 | U56: =IF(D56="demand",Q56*Assumptions!$B$17,ROUNDUP(O56/J56,0)*M56*K56*(1+L56)) -> 30000 | V56: =T56*F56 -> 1.8 | W56: =U56*F56 -> 18 | X56: One page/query assumed; full coverage and pagination unverified. Shared union of followed keys for entity tools; one shared list for global tools. | Y56: Catalogue price/source
A57: T56 | B57: defillama | C57: /equities/v1/companies-list | D57: global | E57: global_daily | F57: 0.0006 | G57: 0 | H57: 0 | I57: 0 | J57: 1 | K57: 1 | L57: 0 | M57: =Profiles!D8 -> 30 | N57: =IF(H57>0,H57,IF(D57="entity",MAX(Assumptions!$B$7,ROUNDUP(Assumptions!$B$2*Assumptions!$B$7*Assumptions!$B$8,0)),1)) -> 1 | O57: =IF(I57>0,I57,IF(D57="entity",MAX(Assumptions!$B$7,ROUNDUP(Assumptions!$B$3*Assumptions!$B$7*Assumptions!$B$8,0)),1)) -> 1 | P57: =ROUNDUP(Assumptions!$B$2*Assumptions!$B$4*Assumptions!$B$5/J57,0)*K57*(1+L57) -> 1100 | Q57: =ROUNDUP(Assumptions!$B$3*Assumptions!$B$4*Assumptions!$B$5/J57,0)*K57*(1+L57) -> 11000 | R57: =P57*F57 -> 0.66 | S57: =Q57*F57 -> 6.6 | T57: =IF(D57="demand",P57*Assumptions!$B$17,ROUNDUP(N57/J57,0)*M57*K57*(1+L57)) -> 30 | U57: =IF(D57="demand",Q57*Assumptions!$B$17,ROUNDUP(O57/J57,0)*M57*K57*(1+L57)) -> 30 | V57: =T57*F57 -> 0.018 | W57: =U57*F57 -> 0.018 | X57: One page/query assumed; full coverage and pagination unverified. Shared union of followed keys for entity tools; one shared list for global tools. | Y57: Catalogue price/source
A58: T57 | B58: defillama | C58: /equities/v1/ohlcv | D58: entity | E58: entity_market | F58: 0.0006 | G58: 0 | H58: 0 | I58: 0 | J58: 1 | K58: 1 | L58: 0 | M58: =Profiles!D2 -> 1716 | N58: =IF(H58>0,H58,IF(D58="entity",MAX(Assumptions!$B$7,ROUNDUP(Assumptions!$B$2*Assumptions!$B$7*Assumptions!$B$8,0)),1)) -> 100 | O58: =IF(I58>0,I58,IF(D58="entity",MAX(Assumptions!$B$7,ROUNDUP(Assumptions!$B$3*Assumptions!$B$7*Assumptions!$B$8,0)),1)) -> 1000 | P58: =ROUNDUP(Assumptions!$B$2*Assumptions!$B$4*Assumptions!$B$5/J58,0)*K58*(1+L58) -> 1100 | Q58: =ROUNDUP(Assumptions!$B$3*Assumptions!$B$4*Assumptions!$B$5/J58,0)*K58*(1+L58) -> 11000 | R58: =P58*F58 -> 0.66 | S58: =Q58*F58 -> 6.6 | T58: =IF(D58="demand",P58*Assumptions!$B$17,ROUNDUP(N58/J58,0)*M58*K58*(1+L58)) -> 171600 | U58: =IF(D58="demand",Q58*Assumptions!$B$17,ROUNDUP(O58/J58,0)*M58*K58*(1+L58)) -> 1716000 | V58: =T58*F58 -> 102.96 | W58: =U58*F58 -> 1029.6 | X58: One page/query assumed; full coverage and pagination unverified. Shared union of followed keys for entity tools; one shared list for global tools. | Y58: Catalogue price/source
A59: T58 | B59: defillama | C59: /equities/v1/onchain | D59: entity | E59: entity_onchain | F59: 0.0006 | G59: 0 | H59: 0 | I59: 0 | J59: 1 | K59: 1 | L59: 0 | M59: =Profiles!D11 -> 720 | N59: =IF(H59>0,H59,IF(D59="entity",MAX(Assumptions!$B$7,ROUNDUP(Assumptions!$B$2*Assumptions!$B$7*Assumptions!$B$8,0)),1)) -> 100 | O59: =IF(I59>0,I59,IF(D59="entity",MAX(Assumptions!$B$7,ROUNDUP(Assumptions!$B$3*Assumptions!$B$7*Assumptions!$B$8,0)),1)) -> 1000 | P59: =ROUNDUP(Assumptions!$B$2*Assumptions!$B$4*Assumptions!$B$5/J59,0)*K59*(1+L59) -> 1100 | Q59: =ROUNDUP(Assumptions!$B$3*Assumptions!$B$4*Assumptions!$B$5/J59,0)*K59*(1+L59) -> 11000 | R59: =P59*F59 -> 0.66 | S59: =Q59*F59 -> 6.6 | T59: =IF(D59="demand",P59*Assumptions!$B$17,ROUNDUP(N59/J59,0)*M59*K59*(1+L59)) -> 72000 | U59: =IF(D59="demand",Q59*Assumptions!$B$17,ROUNDUP(O59/J59,0)*M59*K59*(1+L59)) -> 720000 | V59: =T59*F59 -> 43.2 | W59: =U59*F59 -> 432 | X59: One page/query assumed; full coverage and pagination unverified. Shared union of followed keys for entity tools; one shared list for global tools. | Y59: Catalogue price/source
A60: T59 | B60: defillama | C60: /equities/v1/dimensions | D60: entity | E60: entity_daily | F60: 0.0006 | G60: 0 | H60: 0 | I60: 0 | J60: 1 | K60: 1 | L60: 0 | M60: =Profiles!D7 -> 30 | N60: =IF(H60>0,H60,IF(D60="entity",MAX(Assumptions!$B$7,ROUNDUP(Assumptions!$B$2*Assumptions!$B$7*Assumptions!$B$8,0)),1)) -> 100 | O60: =IF(I60>0,I60,IF(D60="entity",MAX(Assumptions!$B$7,ROUNDUP(Assumptions!$B$3*Assumptions!$B$7*Assumptions!$B$8,0)),1)) -> 1000 | P60: =ROUNDUP(Assumptions!$B$2*Assumptions!$B$4*Assumptions!$B$5/J60,0)*K60*(1+L60) -> 1100 | Q60: =ROUNDUP(Assumptions!$B$3*Assumptions!$B$4*Assumptions!$B$5/J60,0)*K60*(1+L60) -> 11000 | R60: =P60*F60 -> 0.66 | S60: =Q60*F60 -> 6.6 | T60: =IF(D60="demand",P60*Assumptions!$B$17,ROUNDUP(N60/J60,0)*M60*K60*(1+L60)) -> 3000 | U60: =IF(D60="demand",Q60*Assumptions!$B$17,ROUNDUP(O60/J60,0)*M60*K60*(1+L60)) -> 30000 | V60: =T60*F60 -> 1.8 | W60: =U60*F60 -> 18 | X60: One page/query assumed; full coverage and pagination unverified. Shared union of followed keys for entity tools; one shared list for global tools. | Y60: Catalogue price/source
A61: T60 | B61: secform4 | C61: /search | D61: demand | E61: lookup_demand | F61: 0.01 | G61: 0 | H61: 0 | I61: 0 | J61: 1 | K61: 1 | L61: 0 | M61: =Profiles!D9 -> 0 | N61: =IF(H61>0,H61,IF(D61="entity",MAX(Assumptions!$B$7,ROUNDUP(Assumptions!$B$2*Assumptions!$B$7*Assumptions!$B$8,0)),1)) -> 1 | O61: =IF(I61>0,I61,IF(D61="entity",MAX(Assumptions!$B$7,ROUNDUP(Assumptions!$B$3*Assumptions!$B$7*Assumptions!$B$8,0)),1)) -> 1 | P61: =ROUNDUP(Assumptions!$B$2*Assumptions!$B$4*Assumptions!$B$5/J61,0)*K61*(1+L61) -> 1100 | Q61: =ROUNDUP(Assumptions!$B$3*Assumptions!$B$4*Assumptions!$B$5/J61,0)*K61*(1+L61) -> 11000 | R61: =P61*F61 -> 11 | S61: =Q61*F61 -> 110 | T61: =IF(D61="demand",P61*Assumptions!$B$17,ROUNDUP(N61/J61,0)*M61*K61*(1+L61)) -> 550 | U61: =IF(D61="demand",Q61*Assumptions!$B$17,ROUNDUP(O61/J61,0)*M61*K61*(1+L61)) -> 5500 | V61: =T61*F61 -> 5.5 | W61: =U61*F61 -> 55 | X61: One page/query assumed; full coverage and pagination unverified. Shared union of followed keys for entity tools; one shared list for global tools. | Y61: Catalogue price/source
A62: T61 | B62: secform4 | C62: /get_13d_filings | D62: global | E62: global_insider | F62: 0.01 | G62: 0 | H62: 0 | I62: 0 | J62: 1 | K62: 1 | L62: 0 | M62: =Profiles!D6 -> 1408 | N62: =IF(H62>0,H62,IF(D62="entity",MAX(Assumptions!$B$7,ROUNDUP(Assumptions!$B$2*Assumptions!$B$7*Assumptions!$B$8,0)),1)) -> 1 | O62: =IF(I62>0,I62,IF(D62="entity",MAX(Assumptions!$B$7,ROUNDUP(Assumptions!$B$3*Assumptions!$B$7*Assumptions!$B$8,0)),1)) -> 1 | P62: =ROUNDUP(Assumptions!$B$2*Assumptions!$B$4*Assumptions!$B$5/J62,0)*K62*(1+L62) -> 1100 | Q62: =ROUNDUP(Assumptions!$B$3*Assumptions!$B$4*Assumptions!$B$5/J62,0)*K62*(1+L62) -> 11000 | R62: =P62*F62 -> 11 | S62: =Q62*F62 -> 110 | T62: =IF(D62="demand",P62*Assumptions!$B$17,ROUNDUP(N62/J62,0)*M62*K62*(1+L62)) -> 1408 | U62: =IF(D62="demand",Q62*Assumptions!$B$17,ROUNDUP(O62/J62,0)*M62*K62*(1+L62)) -> 1408 | V62: =T62*F62 -> 14.08 | W62: =U62*F62 -> 14.08 | X62: One page/query assumed; full coverage and pagination unverified. Shared union of followed keys for entity tools; one shared list for global tools. | Y62: Catalogue price/source
A63: T62 | B63: secform4 | C63: /get_insider_sales | D63: global | E63: global_insider | F63: 0.01 | G63: 0 | H63: 0 | I63: 0 | J63: 1 | K63: 1 | L63: 0 | M63: =Profiles!D6 -> 1408 | N63: =IF(H63>0,H63,IF(D63="entity",MAX(Assumptions!$B$7,ROUNDUP(Assumptions!$B$2*Assumptions!$B$7*Assumptions!$B$8,0)),1)) -> 1 | O63: =IF(I63>0,I63,IF(D63="entity",MAX(Assumptions!$B$7,ROUNDUP(Assumptions!$B$3*Assumptions!$B$7*Assumptions!$B$8,0)),1)) -> 1 | P63: =ROUNDUP(Assumptions!$B$2*Assumptions!$B$4*Assumptions!$B$5/J63,0)*K63*(1+L63) -> 1100 | Q63: =ROUNDUP(Assumptions!$B$3*Assumptions!$B$4*Assumptions!$B$5/J63,0)*K63*(1+L63) -> 11000 | R63: =P63*F63 -> 11 | S63: =Q63*F63 -> 110 | T63: =IF(D63="demand",P63*Assumptions!$B$17,ROUNDUP(N63/J63,0)*M63*K63*(1+L63)) -> 1408 | U63: =IF(D63="demand",Q63*Assumptions!$B$17,ROUNDUP(O63/J63,0)*M63*K63*(1+L63)) -> 1408 | V63: =T63*F63 -> 14.08 | W63: =U63*F63 -> 14.08 | X63: One page/query assumed; full coverage and pagination unverified. Shared union of followed keys for entity tools; one shared list for global tools. | Y63: Catalogue price/source
A64: T63 | B64: secform4 | C64: /get_significant_insider_buys | D64: global | E64: global_insider | F64: 0.01 | G64: 0 | H64: 0 | I64: 0 | J64: 1 | K64: 1 | L64: 0 | M64: =Profiles!D6 -> 1408 | N64: =IF(H64>0,H64,IF(D64="entity",MAX(Assumptions!$B$7,ROUNDUP(Assumptions!$B$2*Assumptions!$B$7*Assumptions!$B$8,0)),1)) -> 1 | O64: =IF(I64>0,I64,IF(D64="entity",MAX(Assumptions!$B$7,ROUNDUP(Assumptions!$B$3*Assumptions!$B$7*Assumptions!$B$8,0)),1)) -> 1 | P64: =ROUNDUP(Assumptions!$B$2*Assumptions!$B$4*Assumptions!$B$5/J64,0)*K64*(1+L64) -> 1100 | Q64: =ROUNDUP(Assumptions!$B$3*Assumptions!$B$4*Assumptions!$B$5/J64,0)*K64*(1+L64) -> 11000 | R64: =P64*F64 -> 11 | S64: =Q64*F64 -> 110 | T64: =IF(D64="demand",P64*Assumptions!$B$17,ROUNDUP(N64/J64,0)*M64*K64*(1+L64)) -> 1408 | U64: =IF(D64="demand",Q64*Assumptions!$B$17,ROUNDUP(O64/J64,0)*M64*K64*(1+L64)) -> 1408 | V64: =T64*F64 -> 14.08 | W64: =U64*F64 -> 14.08 | X64: One page/query assumed; full coverage and pagination unverified. Shared union of followed keys for entity tools; one shared list for global tools. | Y64: Catalogue price/source
A65: T64 | B65: secform4 | C65: /get_institution_holders | D65: entity | E65: entity_daily | F65: 0.01 | G65: 0 | H65: 0 | I65: 0 | J65: 1 | K65: 1 | L65: 0 | M65: =Profiles!D7 -> 30 | N65: =IF(H65>0,H65,IF(D65="entity",MAX(Assumptions!$B$7,ROUNDUP(Assumptions!$B$2*Assumptions!$B$7*Assumptions!$B$8,0)),1)) -> 100 | O65: =IF(I65>0,I65,IF(D65="entity",MAX(Assumptions!$B$7,ROUNDUP(Assumptions!$B$3*Assumptions!$B$7*Assumptions!$B$8,0)),1)) -> 1000 | P65: =ROUNDUP(Assumptions!$B$2*Assumptions!$B$4*Assumptions!$B$5/J65,0)*K65*(1+L65) -> 1100 | Q65: =ROUNDUP(Assumptions!$B$3*Assumptions!$B$4*Assumptions!$B$5/J65,0)*K65*(1+L65) -> 11000 | R65: =P65*F65 -> 11 | S65: =Q65*F65 -> 110 | T65: =IF(D65="demand",P65*Assumptions!$B$17,ROUNDUP(N65/J65,0)*M65*K65*(1+L65)) -> 3000 | U65: =IF(D65="demand",Q65*Assumptions!$B$17,ROUNDUP(O65/J65,0)*M65*K65*(1+L65)) -> 30000 | V65: =T65*F65 -> 30 | W65: =U65*F65 -> 300 | X65: One page/query assumed; full coverage and pagination unverified. Shared union of followed keys for entity tools; one shared list for global tools. | Y65: Catalogue price/source
A66: T65 | B66: secform4 | C66: /get_insider_buy_sell_ratios | D66: global | E66: global_insider | F66: 0.01 | G66: 0 | H66: 0 | I66: 0 | J66: 1 | K66: 1 | L66: 0 | M66: =Profiles!D6 -> 1408 | N66: =IF(H66>0,H66,IF(D66="entity",MAX(Assumptions!$B$7,ROUNDUP(Assumptions!$B$2*Assumptions!$B$7*Assumptions!$B$8,0)),1)) -> 1 | O66: =IF(I66>0,I66,IF(D66="entity",MAX(Assumptions!$B$7,ROUNDUP(Assumptions!$B$3*Assumptions!$B$7*Assumptions!$B$8,0)),1)) -> 1 | P66: =ROUNDUP(Assumptions!$B$2*Assumptions!$B$4*Assumptions!$B$5/J66,0)*K66*(1+L66) -> 1100 | Q66: =ROUNDUP(Assumptions!$B$3*Assumptions!$B$4*Assumptions!$B$5/J66,0)*K66*(1+L66) -> 11000 | R66: =P66*F66 -> 11 | S66: =Q66*F66 -> 110 | T66: =IF(D66="demand",P66*Assumptions!$B$17,ROUNDUP(N66/J66,0)*M66*K66*(1+L66)) -> 1408 | U66: =IF(D66="demand",Q66*Assumptions!$B$17,ROUNDUP(O66/J66,0)*M66*K66*(1+L66)) -> 1408 | V66: =T66*F66 -> 14.08 | W66: =U66*F66 -> 14.08 | X66: One page/query assumed; full coverage and pagination unverified. Shared union of followed keys for entity tools; one shared list for global tools. | Y66: Catalogue price/source
A67: T66 | B67: secform4 | C67: /get_stock_options | D67: global | E67: global_insider | F67: 0.01 | G67: 0 | H67: 0 | I67: 0 | J67: 1 | K67: 1 | L67: 0 | M67: =Profiles!D6 -> 1408 | N67: =IF(H67>0,H67,IF(D67="entity",MAX(Assumptions!$B$7,ROUNDUP(Assumptions!$B$2*Assumptions!$B$7*Assumptions!$B$8,0)),1)) -> 1 | O67: =IF(I67>0,I67,IF(D67="entity",MAX(Assumptions!$B$7,ROUNDUP(Assumptions!$B$3*Assumptions!$B$7*Assumptions!$B$8,0)),1)) -> 1 | P67: =ROUNDUP(Assumptions!$B$2*Assumptions!$B$4*Assumptions!$B$5/J67,0)*K67*(1+L67) -> 1100 | Q67: =ROUNDUP(Assumptions!$B$3*Assumptions!$B$4*Assumptions!$B$5/J67,0)*K67*(1+L67) -> 11000 | R67: =P67*F67 -> 11 | S67: =Q67*F67 -> 110 | T67: =IF(D67="demand",P67*Assumptions!$B$17,ROUNDUP(N67/J67,0)*M67*K67*(1+L67)) -> 1408 | U67: =IF(D67="demand",Q67*Assumptions!$B$17,ROUNDUP(O67/J67,0)*M67*K67*(1+L67)) -> 1408 | V67: =T67*F67 -> 14.08 | W67: =U67*F67 -> 14.08 | X67: One page/query assumed; full coverage and pagination unverified. Shared union of followed keys for entity tools; one shared list for global tools. | Y67: Catalogue price/source
A68: T67 | B68: secform4 | C68: /get_insider_buys | D68: global | E68: global_insider | F68: 0.01 | G68: 0 | H68: 0 | I68: 0 | J68: 1 | K68: 1 | L68: 0 | M68: =Profiles!D6 -> 1408 | N68: =IF(H68>0,H68,IF(D68="entity",MAX(Assumptions!$B$7,ROUNDUP(Assumptions!$B$2*Assumptions!$B$7*Assumptions!$B$8,0)),1)) -> 1 | O68: =IF(I68>0,I68,IF(D68="entity",MAX(Assumptions!$B$7,ROUNDUP(Assumptions!$B$3*Assumptions!$B$7*Assumptions!$B$8,0)),1)) -> 1 | P68: =ROUNDUP(Assumptions!$B$2*Assumptions!$B$4*Assumptions!$B$5/J68,0)*K68*(1+L68) -> 1100 | Q68: =ROUNDUP(Assumptions!$B$3*Assumptions!$B$4*Assumptions!$B$5/J68,0)*K68*(1+L68) -> 11000 | R68: =P68*F68 -> 11 | S68: =Q68*F68 -> 110 | T68: =IF(D68="demand",P68*Assumptions!$B$17,ROUNDUP(N68/J68,0)*M68*K68*(1+L68)) -> 1408 | U68: =IF(D68="demand",Q68*Assumptions!$B$17,ROUNDUP(O68/J68,0)*M68*K68*(1+L68)) -> 1408 | V68: =T68*F68 -> 14.08 | W68: =U68*F68 -> 14.08 | X68: One page/query assumed; full coverage and pagination unverified. Shared union of followed keys for entity tools; one shared list for global tools. | Y68: Catalogue price/source
A69: T68 | B69: secform4 | C69: /get_company_insider_trading | D69: entity | E69: entity_hourly | F69: 0.01 | G69: 0 | H69: 0 | I69: 0 | J69: 1 | K69: 1 | L69: 0 | M69: =Profiles!D5 -> 352 | N69: =IF(H69>0,H69,IF(D69="entity",MAX(Assumptions!$B$7,ROUNDUP(Assumptions!$B$2*Assumptions!$B$7*Assumptions!$B$8,0)),1)) -> 100 | O69: =IF(I69>0,I69,IF(D69="entity",MAX(Assumptions!$B$7,ROUNDUP(Assumptions!$B$3*Assumptions!$B$7*Assumptions!$B$8,0)),1)) -> 1000 | P69: =ROUNDUP(Assumptions!$B$2*Assumptions!$B$4*Assumptions!$B$5/J69,0)*K69*(1+L69) -> 1100 | Q69: =ROUNDUP(Assumptions!$B$3*Assumptions!$B$4*Assumptions!$B$5/J69,0)*K69*(1+L69) -> 11000 | R69: =P69*F69 -> 11 | S69: =Q69*F69 -> 110 | T69: =IF(D69="demand",P69*Assumptions!$B$17,ROUNDUP(N69/J69,0)*M69*K69*(1+L69)) -> 35200 | U69: =IF(D69="demand",Q69*Assumptions!$B$17,ROUNDUP(O69/J69,0)*M69*K69*(1+L69)) -> 352000 | V69: =T69*F69 -> 352 | W69: =U69*F69 -> 3520 | X69: One page/query assumed; full coverage and pagination unverified. Shared union of followed keys for entity tools; one shared list for global tools. | Y69: Catalogue price/source
A70: T69 | B70: secform4 | C70: /get_hedge_fund_portfolio | D70: entity | E70: entity_daily | F70: 0.01 | G70: 0 | H70: 10 | I70: 10 | J70: 1 | K70: 1 | L70: 0 | M70: =Profiles!D7 -> 30 | N70: =IF(H70>0,H70,IF(D70="entity",MAX(Assumptions!$B$7,ROUNDUP(Assumptions!$B$2*Assumptions!$B$7*Assumptions!$B$8,0)),1)) -> 10 | O70: =IF(I70>0,I70,IF(D70="entity",MAX(Assumptions!$B$7,ROUNDUP(Assumptions!$B$3*Assumptions!$B$7*Assumptions!$B$8,0)),1)) -> 10 | P70: =ROUNDUP(Assumptions!$B$2*Assumptions!$B$4*Assumptions!$B$5/J70,0)*K70*(1+L70) -> 1100 | Q70: =ROUNDUP(Assumptions!$B$3*Assumptions!$B$4*Assumptions!$B$5/J70,0)*K70*(1+L70) -> 11000 | R70: =P70*F70 -> 11 | S70: =Q70*F70 -> 110 | T70: =IF(D70="demand",P70*Assumptions!$B$17,ROUNDUP(N70/J70,0)*M70*K70*(1+L70)) -> 300 | U70: =IF(D70="demand",Q70*Assumptions!$B$17,ROUNDUP(O70/J70,0)*M70*K70*(1+L70)) -> 300 | V70: =T70*F70 -> 3 | W70: =U70*F70 -> 3 | X70: One page/query assumed; full coverage and pagination unverified. Fixed optional universe of 10 keys in both scenarios. | Y70: Catalogue price/source
A71: T70 | B71: secform4 | C71: /get_13g_filings | D71: global | E71: global_insider | F71: 0.01 | G71: 0 | H71: 0 | I71: 0 | J71: 1 | K71: 1 | L71: 0 | M71: =Profiles!D6 -> 1408 | N71: =IF(H71>0,H71,IF(D71="entity",MAX(Assumptions!$B$7,ROUNDUP(Assumptions!$B$2*Assumptions!$B$7*Assumptions!$B$8,0)),1)) -> 1 | O71: =IF(I71>0,I71,IF(D71="entity",MAX(Assumptions!$B$7,ROUNDUP(Assumptions!$B$3*Assumptions!$B$7*Assumptions!$B$8,0)),1)) -> 1 | P71: =ROUNDUP(Assumptions!$B$2*Assumptions!$B$4*Assumptions!$B$5/J71,0)*K71*(1+L71) -> 1100 | Q71: =ROUNDUP(Assumptions!$B$3*Assumptions!$B$4*Assumptions!$B$5/J71,0)*K71*(1+L71) -> 11000 | R71: =P71*F71 -> 11 | S71: =Q71*F71 -> 110 | T71: =IF(D71="demand",P71*Assumptions!$B$17,ROUNDUP(N71/J71,0)*M71*K71*(1+L71)) -> 1408 | U71: =IF(D71="demand",Q71*Assumptions!$B$17,ROUNDUP(O71/J71,0)*M71*K71*(1+L71)) -> 1408 | V71: =T71*F71 -> 14.08 | W71: =U71*F71 -> 14.08 | X71: One page/query assumed; full coverage and pagination unverified. Shared union of followed keys for entity tools; one shared list for global tools. | Y71: Catalogue price/source
A73: ALL 70: redundant reference total | R73: =SUM(R2:R71) -> 929.28 | S73: =SUM(S2:S71) -> 9292.8 | V73: =SUM(V2:V71) -> 23874.218 | W73: =SUM(W2:W71) -> 233674.48
A74: SELECTED tools only: edit Include | R74: =SUMPRODUCT(G2:G71,R2:R71) -> 0 | S74: =SUMPRODUCT(G2:G71,S2:S71) -> 0 | V74: =SUMPRODUCT(G2:G71,V2:V71) -> 0 | W74: =SUMPRODUCT(G2:G71,W2:W71) -> 0

Sheet Budget summary
A1: Family / scenario | B1: Tools | C1: Research USD: 10 | D1: Research USD: 100 | E1: Feed USD: 10 | F1: Feed USD: 100 | G1: Interpretation
A2: Nasdaq | B2: 20 | C2: =SUMIF(Costs!$B$2:$B$71,"nasdaq",Costs!$R$2:$R$71) -> 220 | D2: =SUMIF(Costs!$B$2:$B$71,"nasdaq",Costs!$S$2:$S$71) -> 2200 | E2: =SUMIF(Costs!$B$2:$B$71,"nasdaq",Costs!$V$2:$V$71) -> 4847.48 | F2: =SUMIF(Costs!$B$2:$B$71,"nasdaq",Costs!$W$2:$W$71) -> 44892.98 | G2: Enables all tools in this family, including alternatives and optional assets. Research actions call each family tool. Not a proposed bundle.
A3: Yahoo Finance | B3: 5 | C3: =SUMIF(Costs!$B$2:$B$71,"yahoo-finance",Costs!$R$2:$R$71) -> 275 | D3: =SUMIF(Costs!$B$2:$B$71,"yahoo-finance",Costs!$S$2:$S$71) -> 2750 | E3: =SUMIF(Costs!$B$2:$B$71,"yahoo-finance",Costs!$V$2:$V$71) -> 11307.5 | F3: =SUMIF(Costs!$B$2:$B$71,"yahoo-finance",Costs!$W$2:$W$71) -> 113075 | G3: Enables all tools in this family, including alternatives and optional assets. Research actions call each family tool. Not a proposed bundle.
A4: Finviz | B4: 5 | C4: =SUMIF(Costs!$B$2:$B$71,"finviz",Costs!$R$2:$R$71) -> 55 | D4: =SUMIF(Costs!$B$2:$B$71,"finviz",Costs!$S$2:$S$71) -> 550 | E4: =SUMIF(Costs!$B$2:$B$71,"finviz",Costs!$V$2:$V$71) -> 2244.4 | F4: =SUMIF(Costs!$B$2:$B$71,"finviz",Costs!$W$2:$W$71) -> 22008.4 | G4: Enables all tools in this family, including alternatives and optional assets. Research actions call each family tool. Not a proposed bundle.
A5: MarketBeat | B5: 14 | C5: =SUMIF(Costs!$B$2:$B$71,"marketbeat",Costs!$R$2:$R$71) -> 176 | D5: =SUMIF(Costs!$B$2:$B$71,"marketbeat",Costs!$S$2:$S$71) -> 1760 | E5: =SUMIF(Costs!$B$2:$B$71,"marketbeat",Costs!$V$2:$V$71) -> 2913.5 | F5: =SUMIF(Costs!$B$2:$B$71,"marketbeat",Costs!$W$2:$W$71) -> 29135 | G5: Enables all tools in this family, including alternatives and optional assets. Research actions call each family tool. Not a proposed bundle.
A6: StockAnalysis | B6: 7 | C6: =SUMIF(Costs!$B$2:$B$71,"stockanalysis",Costs!$R$2:$R$71) -> 77 | D6: =SUMIF(Costs!$B$2:$B$71,"stockanalysis",Costs!$S$2:$S$71) -> 770 | E6: =SUMIF(Costs!$B$2:$B$71,"stockanalysis",Costs!$V$2:$V$71) -> 1796.62 | F6: =SUMIF(Costs!$B$2:$B$71,"stockanalysis",Costs!$W$2:$W$71) -> 17830.12 | G6: Enables all tools in this family, including alternatives and optional assets. Research actions call each family tool. Not a proposed bundle.
A7: DefiLlama equities | B7: 8 | C7: =SUMIF(Costs!$B$2:$B$71,"defillama",Costs!$R$2:$R$71) -> 5.28 | D7: =SUMIF(Costs!$B$2:$B$71,"defillama",Costs!$S$2:$S$71) -> 52.8 | E7: =SUMIF(Costs!$B$2:$B$71,"defillama",Costs!$V$2:$V$71) -> 275.658 | F7: =SUMIF(Costs!$B$2:$B$71,"defillama",Costs!$W$2:$W$71) -> 2756.418 | G7: Enables all tools in this family, including alternatives and optional assets. Research actions call each family tool. Not a proposed bundle.
A8: SECForm4.com | B8: 11 | C8: =SUMIF(Costs!$B$2:$B$71,"secform4",Costs!$R$2:$R$71) -> 121 | D8: =SUMIF(Costs!$B$2:$B$71,"secform4",Costs!$S$2:$S$71) -> 1210 | E8: =SUMIF(Costs!$B$2:$B$71,"secform4",Costs!$V$2:$V$71) -> 489.06 | F8: =SUMIF(Costs!$B$2:$B$71,"secform4",Costs!$W$2:$W$71) -> 3976.56 | G8: Enables all tools in this family, including alternatives and optional assets. Research actions call each family tool. Not a proposed bundle.
A10: All 70 reference | C10: =SUM(Costs!$R$2:$R$71) -> 929.28 | D10: =SUM(Costs!$S$2:$S$71) -> 9292.8 | E10: =SUM(Costs!$V$2:$V$71) -> 23874.218 | F10: =SUM(Costs!$W$2:$W$71) -> 233674.48 | G10: Mechanical sum, NOT a recommendation or commercial quote.
A11: Selected tools | C11: =SUMPRODUCT(Costs!$G$2:$G$71,Costs!$R$2:$R$71) -> 0 | D11: =SUMPRODUCT(Costs!$G$2:$G$71,Costs!$S$2:$S$71) -> 0 | E11: =SUMPRODUCT(Costs!$G$2:$G$71,Costs!$V$2:$V$71) -> 0 | F11: =SUMPRODUCT(Costs!$G$2:$G$71,Costs!$W$2:$W$71) -> 0 | G11: Edit Include on Costs to build a non-overlapping selection.
A14: Scale: query keys | B14: USD/call | C14: Daily USD | D14: Hourly news USD | E14: 5-min market USD
A15: 1515 | B15: 0.01 | C15: =A15*B15*Profiles!D7 -> 454.5 | D15: =A15*B15*Profiles!D4 -> 7272 | E15: =A15*B15*Profiles!D2 -> 25997.4 | G15: One entity/call and one page. Company universe coverage and request throughput NOT established.
A16: 10000 | B16: 0.01 | C16: =A16*B16*Profiles!D7 -> 3000 | D16: =A16*B16*Profiles!D4 -> 48000 | E16: =A16*B16*Profiles!D2 -> 171600 | G16: One entity/call and one page. Company universe coverage and request throughput NOT established.
A17: 50000 | B17: 0.01 | C17: =A17*B17*Profiles!D7 -> 15000 | D17: =A17*B17*Profiles!D4 -> 240000 | E17: =A17*B17*Profiles!D2 -> 858000 | G17: One entity/call and one page. Company universe coverage and request throughput NOT established.

Sheet Sources
A1: Source ID | B1: Title / supports | C1: Primary URL | D1: Evidence boundary
A2: S1 | B2: Monid finance directory and paginated public catalogue | C2: https://monid.ai/tools?c=finance | D2: Official publisher/operator/regulator source; scope-specific statements do not establish Monid delivery or downstream permission.
A3: S2 | B3: Monid public finance endpoint metadata | C3: https://api.monid.ai/public/v1/endpoints?category=finance&limit=24 | D3: Official publisher/operator/regulator source; scope-specific statements do not establish Monid delivery or downstream permission.
A4: S3 | B4: StockAnalysis: no API/MCP or programmatic redistribution rights, 8 July 2026 | C4: https://stockanalysis.com/help/faq/api-access/ | D4: Official publisher/operator/regulator source; scope-specific statements do not establish Monid delivery or downstream permission.
A5: S4 | B5: SECForm4 significant buys: delay and selection thresholds | C5: https://www.secform4.com/significant-buys | D5: Official publisher/operator/regulator source; scope-specific statements do not establish Monid delivery or downstream permission.
A6: S5 | B6: DefiLlama official API documentation and direct Pro pricing | C6: https://api-docs.defillama.com/ | D6: Official publisher/operator/regulator source; scope-specific statements do not establish Monid delivery or downstream permission.
A7: S6 | B7: DefiLlama official Pro endpoint documentation | C7: https://github.com/DefiLlama/api-docs/blob/main/llms-pro.txt | D7: Official publisher/operator/regulator source; scope-specific statements do not establish Monid delivery or downstream permission.
A8: S7 | B8: Monid endpoint inspection documentation | C8: https://monid.ai/docs/api/inspect | D8: Official publisher/operator/regulator source; scope-specific statements do not establish Monid delivery or downstream permission.
A9: S8 | B9: Monid execution documentation | C9: https://monid.ai/docs/api/run | D9: Official publisher/operator/regulator source; scope-specific statements do not establish Monid delivery or downstream permission.
A10: S9 | B10: Parse own documentation: independent Nasdaq wrapper | C10: https://parse.bot/marketplace/8357401b-21c5-4fa5-8701-fff62d9a9922/nasdaq-com-api | D10: Operator statement about its own independent wrapper; Monid relationship unverified.
A11: S10 | B11: Parse own documentation: independent Yahoo wrapper | C11: https://parse.bot/marketplace/417d966a-b180-44b0-80e5-477772dfc4e2/yahoofinance-com-api | D11: Operator statement about its own independent wrapper; Monid relationship unverified.
A12: S11 | B12: Parse own documentation: independent Finviz wrapper | C12: https://parse.bot/marketplace/09c62661-67ab-42f3-bdbe-e4f90fbd888d/finviz-com-api | D12: Operator statement about its own independent wrapper; Monid relationship unverified.
... A62: S61 | B62: Monid server integration documentation | C62: https://monid.ai/docs/integrations/overview | D62: Official publisher/operator/regulator source; scope-specific statements do not establish Monid delivery or downstream permission.
